src/mux2.v
module mux2 #(parameter WIDTH = 32)(
    input wire seletor,
    input wire [WIDTH-1:0] entrada1,
    input wire [WIDTH-1:0] entrada2,
    output wire [WIDTH-1:0] saida
);
    assign saida = (seletor) ? entrada2 : entrada1;

endmodule

src/data_memory.v
module data_memory(
    input wire clock,
    input wire MemRead, MemWrite,
    input wire [31:0] endereco,
    input wire [31:0] write_data,
    output wire [31:0] read_data
);
    reg [31:0] memoria [0:255];

    // Inicializar memória com zeros para debug
    initial begin
        for (integer i = 0; i < 256; i = i + 1) begin
            memoria[i] = 32'h00000000;
        end
    end

    // Leitura (word-aligned, divide por 4)
    assign read_data = MemRead ? memoria[endereco[9:2]] : 32'b0;

    // Escrita
    always @(posedge clock) begin
        if (MemWrite) begin
            memoria[endereco[9:2]] <= write_data;
            // Debug da escrita
            $display("DEBUG: Escrevendo endereco[%0d] = %0d (addr_original=%0d)", 
                    endereco[9:2], write_data, endereco);
        end
    end

endmodule

src/alu.v
module alu(
    input wire [31:0] entrada1,
    input wire [31:0] entrada2,
    input wire [3:0] alu_control,
    output reg [31:0] resultado,
    output wire zero
);

    assign zero = (resultado == 32'b0);
    always @(*) begin
        case (alu_control)
           4'b0010: resultado = entrada1 + entrada2;                // ADD
            4'b0110: resultado = entrada1 - entrada2;                // SUB
            4'b0000: resultado = entrada1 & entrada2;                // AND
            4'b0001: resultado = entrada1 | entrada2;                // OR
            4'b0100: resultado = entrada1 ^ entrada2;                // XOR
            4'b0101: resultado = ~(entrada1 | entrada2);             // NOR
            4'b0111: resultado = ($signed(entrada1) < $signed(entrada2)) ? 32'd1 : 32'd0; // SLT (se quiser)
            4'b1000: resultado = entrada1 << entrada2[4:0];          // SLL
            4'b1001: resultado = entrada1 >> entrada2[4:0];          // SRL
            default: resultado = 32'b0;
        endcase
    end

endmodule

src/alu_control.v
module alu_control(
    input  wire [1:0] ALUOp,      // vem do control unit
    input  wire [2:0] funct3,     // instrução
    input  wire [6:0] funct7,     // instrução (usamos bit[5] para distinguir SRL/SRA e ADD/SUB)
    output reg  [3:0] alu_control // código para a ALU
);

    always @(*) begin
        // default
        alu_control = 4'b0000; // ADD por padrão

        case (ALUOp)
            2'b00: begin
                // ALUOp=00: Para loads, stores, e instruções I-type imediatas
                // NOTA: funct3=010 em loads/stores deve usar ADD, não SLT!
                case (funct3)
                    3'b000: alu_control = 4'b0000; // ADD / ADDI / LW / SW
                    3'b001: alu_control = 4'b1000; // SLLI
                    3'b010: alu_control = 4'b0000; // LW/SW (usa ADD) / SLTI - CORRIGIDO!
                    3'b011: alu_control = 4'b0111; // SLTIU (unsigned)
                    3'b100: alu_control = 4'b0100; // XORI
                    3'b101: begin                   // SRLI / SRAI (depende de funct7[5])
                        if (funct7[5]) alu_control = 4'b1010; // SRAI
                        else           alu_control = 4'b1001; // SRLI
                    end
                    3'b110: alu_control = 4'b0011; // ORI
                    3'b111: alu_control = 4'b0010; // ANDI
                    default: alu_control = 4'b0000;
                endcase
            end

            2'b01: begin
                // Branches — normalmente comparam usando SUB (BEQ/BNE) e outros sinais externos interpretam resultado
                alu_control = 4'b0001; // SUB
            end

            2'b10: begin
                // R-type: usar funct3 e funct7
                case (funct3)
                    3'b000: begin
                        // ADD or SUB (funct7 = 0100000 indica SUB em RV32)
                        if (funct7 == 7'b0100000) alu_control = 4'b0001; // SUB
                        else                      alu_control = 4'b0000; // ADD
                    end
                    3'b001: alu_control = 4'b1000; // SLL
                    3'b010: alu_control = 4'b0110; // SLT (signed)
                    3'b011: alu_control = 4'b0111; // SLTU (unsigned)
                    3'b100: alu_control = 4'b0100; // XOR
                    3'b101: begin
                        // SRL or SRA (funct7[5] == 1 -> SRA)
                        if (funct7[5]) alu_control = 4'b1010; // SRA
                        else           alu_control = 4'b1001; // SRL
                    end
                    3'b110: alu_control = 4'b0011; // OR
                    3'b111: alu_control = 4'b0010; // AND
                    default: alu_control = 4'b0000;
                endcase
            end

            default: begin
                // segurança: ADD por padrão
                alu_control = 4'b0000;
            end
        endcase
    end

endmodule

src/imm_gen.v
module imm_gen (
    input  wire [31:0] instrucao,
    output reg  [31:0] imm_out
);

    wire [6:0] opcode = instrucao[6:0];

    always @(*) begin
        case (opcode)
            // I-type (ex.: addi, lw, jalr)
            7'b0000011, // LW
            7'b0010011, // ADDI
            7'b1100111: // JALR
                imm_out = {{20{instrucao[31]}}, instrucao[31:20]};

            // S-type (ex.: sw)
            7'b0100011:
                imm_out = {{20{instrucao[31]}}, instrucao[31:25], instrucao[11:7]};

            // B-type (ex.: beq, bne) - CORRIGIDO
            7'b1100011:
                imm_out = {{19{instrucao[31]}}, instrucao[31], instrucao[7],
                           instrucao[30:25], instrucao[11:8], 1'b0};

            // U-type (ex.: lui, auipc)
            7'b0110111, // LUI
            7'b0010111: // AUIPC
                imm_out = {instrucao[31:12], 12'b0};

            // J-type (ex.: jal)
            7'b1101111:
                imm_out = {{11{instrucao[31]}}, instrucao[31],
                           instrucao[19:12], instrucao[20],
                           instrucao[30:21], 1'b0};

            // Default (R-type ou instrução inválida)
            default:
                imm_out = 32'b0;
        endcase
    end

endmodule

src/register.v
module register(
    input wire clock, RegWrite,
    input wire [4:0] rs1, rs2, rd,
    input wire [31:0] write_data,
    output reg [31:0] read_data1, read_data2
);
    reg [31:0] registradores [0:31];
    integer i;

    initial begin
        for (i = 0; i < 32; i = i + 1) begin
            registradores[i] = 32'b0;
        end
    end

    always @(posedge clock) begin
        if (RegWrite && rd != 0) begin
            registradores[rd] = write_data;
        end
    end

    always @(*) begin
        read_data1 = (rs1 == 0) ? 0 : registradores[rs1];
        read_data2 = (rs2 == 0) ? 0 : registradores[rs2];
    end

endmodule

src/control.v
module control(
    input wire [6:0] opcode,
    output reg Branch, MemRead, MemtoReg, MemWrite, ALUSrc, RegWrite,
    output logic [1:0] ALUOp    
);

    always @(*) begin
        Branch = 1'b0;
        MemRead = 1'b0;
        MemtoReg = 1'b0;
        MemWrite = 1'b0;
        ALUSrc = 1'b0;
        RegWrite = 1'b0;
        ALUOp = 2'b00;
        
        case(opcode)
            7'b0110011: begin // R-type
                RegWrite = 1'b1;
                ALUOp = 2'b10;
                ALUSrc = 1'b0;
                MemtoReg = 1'b0;
            end
            7'b0000011: begin // Load
                MemRead = 1'b1;
                MemtoReg = 1'b1;
                RegWrite = 1'b1;
                ALUSrc = 1'b1;
                ALUOp = 2'b00;
            end
            7'b0100011: begin // Store
                MemWrite = 1'b1;
                ALUSrc = 1'b1;
                ALUOp = 2'b00;
            end
            7'b1100011: begin // Branch
                Branch = 1'b1;
                ALUOp = 2'b01;
                ALUSrc = 1'b0;
            end
           default: begin
           end
        endcase
    end

endmodule

src/instruction_memory.v
module instruction_memory(
    input wire [31:0]endereco,
    output wire [31:0] instrucao
);
    reg [31:0] memoria [0:63];

    initial begin
        for (integer i = 0; i < 64; i = i + 1) begin
            memoria[i] = 32'b00000000000000000000000000010011; // Instrução NOP (No Operation)
        end
         // Carregar programa
        $readmemb("programa.bin", memoria);
        
        // Debug: mostrar instruções carregadas
        $display("=== INSTRUÇÕES CARREGADAS ===");
        $display("memoria[0] = %b", memoria[0]);
        $display("memoria[1] = %b", memoria[1]); 
        $display("memoria[2] = %b", memoria[2]);
        $display("memoria[3] = %b", memoria[3]);
        $display("memoria[4] = %b", memoria[4]);
    end

    assign instrucao = memoria[endereco[9:2]];
endmodule

src/pc.v
module pc(
    input wire clock,
    input wire reset, pc_write,
    input wire [31:0] pc_prox, 
    output reg [31:0] pc
);

    always @(posedge clock or posedge reset) begin
        if (reset)
            pc <= 0;
        else if (pc_write)
            pc <= pc_prox;
    end

endmodule

src/cpu.v
module cpu (
    input wire clock,
    input wire reset
);

    // PC e Instrução
    wire [31:0] pc, pc_prox, pc_plus4;
    wire [31:0] instrucao;
    wire pc_write;

    assign pc_plus4 = pc + 32'd4;

    pc pc_reg(
        .clock(clock),
        .reset(reset),
        .pc_prox(pc_prox),
        .pc(pc),
        .pc_write(pc_write)
    );

    instruction_memory InstMem (
        .endereco(pc),
        .instrucao(instrucao)
    );

    // Decodificação
    wire [6:0] opcode = instrucao[6:0];
    wire [4:0] rd     = instrucao[11:7];
    wire [2:0] funct3 = instrucao[14:12];
    wire [4:0] rs1    = instrucao[19:15];
    wire [4:0] rs2    = instrucao[24:20];
    wire [6:0] funct7 = instrucao[31:25];

    // Registradores da instrução anterior (pipeline simples de 1 estágio)
    reg [4:0] prev_rd;
    reg prev_RegWrite;
    reg stall_cycle;

    wire [31:0] read_data1, read_data2;
    wire [31:0] immediate;

    wire Branch, MemRead, MemWrite, ALUSrc, RegWrite;
    wire MemtoReg;
    wire [1:0] ALUOp; 
    
    // Detecção de hazard simplificada - só 1 ciclo de stall
    wire raw_hazard = prev_RegWrite && prev_rd != 5'b0 && 
                      ((prev_rd == rs1 && rs1 != 5'b0) || 
                       (prev_rd == rs2 && rs2 != 5'b0));
    
    // Se há hazard, insere um stall
    assign pc_write = ~raw_hazard;
    
    // Durante stall, desabilita TODOS os controles de escrita
    wire RegWrite_safe = RegWrite & ~raw_hazard;
    wire MemWrite_safe = MemWrite & ~raw_hazard;

    control ctrl(
        .opcode(opcode),
        .Branch(Branch),
        .MemRead(MemRead),
        .MemtoReg(MemtoReg),
        .MemWrite(MemWrite),
        .ALUSrc(ALUSrc),
        .RegWrite(RegWrite),
        .ALUOp(ALUOp)
    );

    register registradores(
        .clock(clock),
        .RegWrite(RegWrite_safe),
        .rs1(rs1),
        .rs2(rs2),
        .rd(rd),
        .write_data(write_back_data),
        .read_data1(read_data1),
        .read_data2(read_data2)
    );

    imm_gen immGen(
        .instrucao(instrucao),
        .imm_out(immediate)
    );

    // ALU
    wire [3:0] alu_control;
    wire [31:0] alu_entrada2 = ALUSrc ? immediate : read_data2;
    wire [31:0] alu_result;
    wire zero;

    alu_control aluCtrl(
        .ALUOp(ALUOp),
        .funct3(funct3),
        .funct7(funct7),
        .alu_control(alu_control)
    );

    alu alu(
        .entrada1(read_data1),
        .entrada2(alu_entrada2),
        .alu_control(alu_control),
        .resultado(alu_result),
        .zero(zero)
    );

    // Memória de Dados
    wire [31:0] MemRead_data;

    data_memory dataMem(
        .clock(clock),
        .MemRead(MemRead),
        .MemWrite(MemWrite_safe),
        .endereco(alu_result),
        .write_data(read_data2),
        .read_data(MemRead_data)
    );

    // Write Back
    wire [31:0] write_back_data;

    mux2 #(.WIDTH(32)) write_back_mux(
        .seletor(MemtoReg),
        .entrada1(alu_result),
        .entrada2(MemRead_data),
        .saida(write_back_data)
    );

    // Controle de Desvio (Branch)
    wire [31:0] branch_alvo = pc + immediate;
    wire branch_taken = Branch & zero;

    mux2 #(.WIDTH(32)) pc_mux(
        .seletor(branch_taken),
        .entrada1(pc_plus4),
        .entrada2(branch_alvo),
        .saida(pc_prox)
    );
    
    // Pipeline tracking corrigido
    always @(posedge clock or posedge reset) begin
        if (reset) begin
            prev_rd <= 5'b0;
            prev_RegWrite <= 1'b0;
            stall_cycle <= 1'b0;
        end else begin
            // Sempre atualiza, mas durante stall desabilita prev_RegWrite
            // para que no próximo ciclo não detecte hazard novamente
            if (raw_hazard) begin
                // Durante stall, mantém prev_rd mas desabilita prev_RegWrite
                prev_RegWrite <= 1'b0;
                stall_cycle <= 1'b1;
            end else begin
                // Operação normal
                prev_rd <= rd;
                prev_RegWrite <= RegWrite;
                stall_cycle <= 1'b0;
            end
        end
    end

endmodule

src/testbench.v
`timescale 1ns/1ps

module testbench_simple;
    reg clock, reset;
    integer cycle_count;
    integer errors;

    cpu uut (
        .clock(clock),
        .reset(reset)
    );

    initial begin
        $dumpfile("simple_hazard.vcd");
        $dumpvars(0, uut);

        // Primeiro decodificar as instruções manualmente
        $display("\n=== ANÁLISE MANUAL DAS INSTRUÇÕES ===");
        decode_manual();

        clock = 0;
        reset = 1;
        cycle_count = 0;

        #10;
        reset = 0;

        // Executar por mais ciclos
        #200;

        $display("\n=== RESULTADO FINAL ===");
        $display("x0 = %0d", uut.registradores.registradores[0]);
        $display("x1 = %0d (esperado: 10)", uut.registradores.registradores[1]);
        $display("x2 = %0d (esperado: 3)", uut.registradores.registradores[2]);
        $display("x3 = %0d (esperado: 13)", uut.registradores.registradores[3]);
        $display("x4 = %0d (esperado: 7)", uut.registradores.registradores[4]);
        $display("x5 = %0d (esperado: 5)", uut.registradores.registradores[5]);

        // Verificação
        errors = 0;
        if (uut.registradores.registradores[1] != 10) errors = errors + 1;
        if (uut.registradores.registradores[2] != 3) errors = errors + 1;
        if (uut.registradores.registradores[3] != 13) errors = errors + 1;
        if (uut.registradores.registradores[4] != 7) errors = errors + 1;
        if (uut.registradores.registradores[5] != 5) errors = errors + 1;

        if (errors == 0) begin
            $display("\n🎉 SUCESSO! Stalls resolveram os hazards!");
        end else begin
            $display("\n❌ %0d erros restantes", errors);
        end

        $finish;
    end

    // Task para decodificar instruções manualmente
    task decode_manual;
        reg [31:0] instr;
        begin
            // Instrução 0: 00a00093
            instr = 32'h00a00093;
            $display("Instr[0]: %b → ADDI x%0d, x%0d, %0d", 
                     instr, instr[11:7], instr[19:15], $signed(instr[31:20]));
            
            // Instrução 1: 00300213  
            instr = 32'h00300213;
            $display("Instr[1]: %b → ADDI x%0d, x%0d, %0d", 
                     instr, instr[11:7], instr[19:15], $signed(instr[31:20]));
            
            // Instrução 2: 002081b3
            instr = 32'h002081b3;
            $display("Instr[2]: %b → ADD x%0d, x%0d, x%0d", 
                     instr, instr[11:7], instr[19:15], instr[24:20]);
            
            // Instrução 3: 40208233
            instr = 32'h40208233;
            $display("Instr[3]: %b → SUB x%0d, x%0d, x%0d", 
                     instr, instr[11:7], instr[19:15], instr[24:20]);
            
            // Instrução 4: ffb08293
            instr = 32'hffb08293;
            $display("Instr[4]: %b → ADDI x%0d, x%0d, %0d", 
                     instr, instr[11:7], instr[19:15], $signed(instr[31:20]));
        end
    endtask

    // Monitor com informações de hazard
    always @(posedge clock) begin
        if (!reset) begin
            cycle_count = cycle_count + 1;
            
            if (cycle_count <= 20) begin // Mais ciclos para ver stalls
                $display("\n=== Ciclo %0d ===", cycle_count);
                
                if (uut.pc_write) begin
                    $display("PC=%0d → Instr: %h", uut.pc, uut.instrucao);
                    $display("Decodificado: rd=%0d, rs1=%0d, rs2=%0d", 
                            uut.rd, uut.rs1, uut.rs2);
                    $display("read_data1=%0d (x%0d), read_data2=%0d (x%0d)", 
                            uut.read_data1, uut.rs1, uut.read_data2, uut.rs2);
                    $display("prev_rd=%0d, prev_RegWrite=%b", uut.prev_rd, uut.prev_RegWrite);
                end else begin
                    $display("⏸️  STALL: PC=%0d (hazard detectado)", uut.pc);
                    $display("   prev_rd=%0d conflita com rs1=%0d ou rs2=%0d", 
                            uut.prev_rd, uut.rs1, uut.rs2);
                    $display("   raw_hazard=%b (rs1_hazard=%b, rs2_hazard=%b)", 
                            uut.raw_hazard,
                            (uut.prev_RegWrite && uut.prev_rd != 5'b0 && uut.prev_rd == uut.rs1 && uut.rs1 != 5'b0),
                            (uut.prev_RegWrite && uut.prev_rd != 5'b0 && uut.prev_rd == uut.rs2 && uut.rs2 != 5'b0));
                end
                
                if (uut.RegWrite_safe && uut.rd != 0) begin
                    $display("✅ Escrevendo x%0d = %0d", uut.rd, uut.write_back_data);
                end
                
                // Mostrar estado dos registradores importantes
                $display("Registradores: x1=%0d, x2=%0d, x3=%0d, x4=%0d, x5=%0d",
                        uut.registradores.registradores[1],
                        uut.registradores.registradores[2], 
                        uut.registradores.registradores[3],
                        uut.registradores.registradores[4],
                        uut.registradores.registradores[5]);
            end
        end
    end

    always begin
        #5 clock = ~clock;
    end

endmodule

src/simple_hazard.vcd
$date
	Sun Aug 10 22:00:25 2025
$end
$version
	Icarus Verilog
$end
$timescale
	1ps
$end
$scope module testbench_simple $end
$scope module uut $end
$var wire 1 ! MemWrite_safe $end
$var wire 1 " RegWrite_safe $end
$var wire 1 # branch_taken $end
$var wire 1 $ clock $end
$var wire 1 % pc_write $end
$var wire 1 & raw_hazard $end
$var wire 1 ' reset $end
$var wire 1 ( zero $end
$var wire 32 ) write_back_data [31:0] $end
$var wire 5 * rs2 [4:0] $end
$var wire 5 + rs1 [4:0] $end
$var wire 32 , read_data2 [31:0] $end
$var wire 32 - read_data1 [31:0] $end
$var wire 5 . rd [4:0] $end
$var wire 32 / pc_prox [31:0] $end
$var wire 32 0 pc_plus4 [31:0] $end
$var wire 32 1 pc [31:0] $end
$var wire 7 2 opcode [6:0] $end
$var wire 32 3 instrucao [31:0] $end
$var wire 32 4 immediate [31:0] $end
$var wire 7 5 funct7 [6:0] $end
$var wire 3 6 funct3 [2:0] $end
$var wire 32 7 branch_alvo [31:0] $end
$var wire 32 8 alu_result [31:0] $end
$var wire 32 9 alu_entrada2 [31:0] $end
$var wire 4 : alu_control [3:0] $end
$var wire 1 ; RegWrite $end
$var wire 1 < MemtoReg $end
$var wire 1 = MemWrite $end
$var wire 32 > MemRead_data [31:0] $end
$var wire 1 ? MemRead $end
$var wire 1 @ Branch $end
$var wire 1 A ALUSrc $end
$var wire 2 B ALUOp [1:0] $end
$var reg 1 C prev_RegWrite $end
$var reg 5 D prev_rd [4:0] $end
$var reg 1 E stall_cycle $end
$scope module InstMem $end
$var wire 32 F instrucao [31:0] $end
$var wire 32 G endereco [31:0] $end
$scope begin $ivl_for_loop1 $end
$var integer 32 H i [31:0] $end
$upscope $end
$upscope $end
$scope module alu $end
$var wire 32 I entrada2 [31:0] $end
$var wire 1 ( zero $end
$var wire 32 J entrada1 [31:0] $end
$var wire 4 K alu_control [3:0] $end
$var reg 32 L resultado [31:0] $end
$upscope $end
$scope module aluCtrl $end
$var wire 3 M funct3 [2:0] $end
$var wire 7 N funct7 [6:0] $end
$var wire 2 O ALUOp [1:0] $end
$var reg 4 P alu_control [3:0] $end
$upscope $end
$scope module ctrl $end
$var wire 7 Q opcode [6:0] $end
$var reg 2 R ALUOp [1:0] $end
$var reg 1 A ALUSrc $end
$var reg 1 @ Branch $end
$var reg 1 ? MemRead $end
$var reg 1 = MemWrite $end
$var reg 1 < MemtoReg $end
$var reg 1 ; RegWrite $end
$upscope $end
$scope module dataMem $end
$var wire 1 ? MemRead $end
$var wire 1 ! MemWrite $end
$var wire 1 $ clock $end
$var wire 32 S endereco [31:0] $end
$var wire 32 T write_data [31:0] $end
$var wire 32 U read_data [31:0] $end
$scope begin $ivl_for_loop0 $end
$var integer 32 V i [31:0] $end
$upscope $end
$upscope $end
$scope module immGen $end
$var wire 32 W instrucao [31:0] $end
$var wire 7 X opcode [6:0] $end
$var reg 32 Y imm_out [31:0] $end
$upscope $end
$scope module pc_mux $end
$var wire 32 Z entrada1 [31:0] $end
$var wire 32 [ entrada2 [31:0] $end
$var wire 1 # seletor $end
$var wire 32 \ saida [31:0] $end
$upscope $end
$scope module pc_reg $end
$var wire 1 $ clock $end
$var wire 32 ] pc_prox [31:0] $end
$var wire 1 % pc_write $end
$var wire 1 ' reset $end
$var reg 32 ^ pc [31:0] $end
$upscope $end
$scope module registradores $end
$var wire 1 " RegWrite $end
$var wire 1 $ clock $end
$var wire 5 _ rd [4:0] $end
$var wire 5 ` rs1 [4:0] $end
$var wire 5 a rs2 [4:0] $end
$var wire 32 b write_data [31:0] $end
$var reg 32 c read_data1 [31:0] $end
$var reg 32 d read_data2 [31:0] $end
$var integer 32 e i [31:0] $end
$upscope $end
$scope module write_back_mux $end
$var wire 32 f entrada1 [31:0] $end
$var wire 32 g entrada2 [31:0] $end
$var wire 1 < seletor $end
$var wire 32 h saida [31:0] $end
$upscope $end
$upscope $end
$upscope $end
$enddefinitions $end
#0
$dumpvars
b1010 h
b0 g
b1010 f
b100000 e
b0 d
b0 c
b1010 b
b1010 a
b0 `
b1 _
b0 ^
b100 ]
b100 \
b1010 [
b100 Z
b1010 Y
b10011 X
b101000000000000010010011 W
b100000000 V
b0 U
b0 T
b1010 S
b0 R
b10011 Q
b0 P
b0 O
b0 N
b0 M
b1010 L
b0 K
b0 J
b1010 I
b1000000 H
b0 G
b101000000000000010010011 F
0E
b0 D
0C
b0 B
1A
0@
0?
b0 >
0=
0<
1;
b0 :
b1010 9
b1010 8
b1010 7
b0 6
b0 5
b1010 4
b101000000000000010010011 3
b10011 2
b0 1
b100 0
b100 /
b1 .
b0 -
b0 ,
b0 +
b1010 *
b1010 )
0(
1'
0&
1%
0$
0#
1"
0!
$end
#5000
1$
#10000
0$
0'
#15000
b11 )
b11 b
b11 h
b11 8
b11 L
b11 S
b11 f
b11 9
b11 I
b11 4
b11 Y
b11 *
b11 a
b10 .
b10 _
b1100000000000100010011 3
b1100000000000100010011 F
b1100000000000100010011 W
b1000 /
b1000 \
b1000 ]
b111 7
b111 [
b1000 0
b1000 Z
b100 1
b100 G
b100 ^
1C
b1 D
1$
#20000
0$
#25000
0"
0%
1&
b1101 )
b1101 b
b1101 h
b1101 8
b1101 L
b1101 S
b1101 f
b11 ,
b11 T
b11 d
b1010 -
b1010 J
b1010 c
b10 B
b10 O
b10 R
1;
0A
b0 4
b0 Y
b110011 X
b10 *
b10 a
b1 +
b1 `
b11 .
b11 _
b110011 2
b110011 Q
b1000001000000110110011 3
b1000001000000110110011 F
b1000001000000110110011 W
b1100 /
b1100 \
b1100 ]
b10 D
b1000 7
b1000 [
b1100 0
b1100 Z
b1000 1
b1000 G
b1000 ^
1$
#30000
0$
#35000
1"
1%
0&
1E
0C
1$
#40000
0$
#45000
b111 )
b111 b
b111 h
b111 8
b111 L
b111 S
b111 f
b1 :
b1 K
b1 P
b100000 5
b100000 N
b100 .
b100 _
b1000000001000001000001000110011 3
b1000000001000001000001000110011 F
b1000000001000001000001000110011 W
b10000 /
b10000 \
b10000 ]
0E
1C
b11 D
b1100 7
b1100 [
b10000 0
b10000 Z
b1100 1
b1100 G
b1100 ^
1$
#50000
0$
#55000
b101 )
b101 b
b101 h
b101 8
b101 L
b101 S
b101 f
b11111111111111111111111111111011 9
b11111111111111111111111111111011 I
b0 :
b0 K
b0 P
b0 ,
b0 T
b0 d
1A
b0 B
b0 O
b0 R
1;
b11111111111111111111111111111011 4
b11111111111111111111111111111011 Y
b10011 X
b1111111 5
b1111111 N
b11011 *
b11011 a
b101 .
b101 _
b10011 2
b10011 Q
b11111111101100001000001010010011 3
b11111111101100001000001010010011 F
b11111111101100001000001010010011 W
b10100 /
b10100 \
b10100 ]
b1011 7
b1011 [
b10100 0
b10100 Z
b10000 1
b10000 G
b10000 ^
b100 D
1$
#60000
0$
#65000
b0 )
b0 b
b0 h
1(
b0 8
b0 L
b0 S
b0 f
b0 9
b0 I
b0 -
b0 J
b0 c
b0 4
b0 Y
b0 5
b0 N
b0 *
b0 a
b0 +
b0 `
b0 .
b0 _
b10011 3
b10011 F
b10011 W
b11000 /
b11000 \
b11000 ]
b101 D
b10100 7
b10100 [
b11000 0
b11000 Z
b10100 1
b10100 G
b10100 ^
1$
#70000
0$
#75000
b11100 /
b11100 \
b11100 ]
b11000 7
b11000 [
b11100 0
b11100 Z
b11000 1
b11000 G
b11000 ^
b0 D
1$
#80000
0$
#85000
b100000 /
b100000 \
b100000 ]
b11100 7
b11100 [
b100000 0
b100000 Z
b11100 1
b11100 G
b11100 ^
1$
#90000
0$
#95000
b100100 /
b100100 \
b100100 ]
b100000 7
b100000 [
b100100 0
b100100 Z
b100000 1
b100000 G
b100000 ^
1$
#100000
0$
#105000
b101000 /
b101000 \
b101000 ]
b100100 7
b100100 [
b101000 0
b101000 Z
b100100 1
b100100 G
b100100 ^
1$
#110000
0$
#115000
b101100 /
b101100 \
b101100 ]
b101000 7
b101000 [
b101100 0
b101100 Z
b101000 1
b101000 G
b101000 ^
1$
#120000
0$
#125000
b110000 /
b110000 \
b110000 ]
b101100 7
b101100 [
b110000 0
b110000 Z
b101100 1
b101100 G
b101100 ^
1$
#130000
0$
#135000
b110100 /
b110100 \
b110100 ]
b110000 7
b110000 [
b110100 0
b110100 Z
b110000 1
b110000 G
b110000 ^
1$
#140000
0$
#145000
b111000 /
b111000 \
b111000 ]
b110100 7
b110100 [
b111000 0
b111000 Z
b110100 1
b110100 G
b110100 ^
1$
#150000
0$
#155000
b111100 /
b111100 \
b111100 ]
b111000 7
b111000 [
b111100 0
b111100 Z
b111000 1
b111000 G
b111000 ^
1$
#160000
0$
#165000
b1000000 /
b1000000 \
b1000000 ]
b111100 7
b111100 [
b1000000 0
b1000000 Z
b111100 1
b111100 G
b111100 ^
1$
#170000
0$
#175000
b1000100 /
b1000100 \
b1000100 ]
b1000000 7
b1000000 [
b1000100 0
b1000100 Z
b1000000 1
b1000000 G
b1000000 ^
1$
#180000
0$
#185000
b1001000 /
b1001000 \
b1001000 ]
b1000100 7
b1000100 [
b1001000 0
b1001000 Z
b1000100 1
b1000100 G
b1000100 ^
1$
#190000
0$
#195000
b1001100 /
b1001100 \
b1001100 ]
b1001000 7
b1001000 [
b1001100 0
b1001100 Z
b1001000 1
b1001000 G
b1001000 ^
1$
#200000
0$
#205000
b1010000 /
b1010000 \
b1010000 ]
b1001100 7
b1001100 [
b1010000 0
b1010000 Z
b1001100 1
b1001100 G
b1001100 ^
1$
