src/mux2.v
module mux2 #(parameter WIDTH = 32)(
    input wire seletor,
    input wire [WIDTH-1:0] entrada1,
    input wire [WIDTH-1:0] entrada2,
    output wire [WIDTH-1:0] saida
);
    assign saida = (seletor) ? entrada2 : entrada1;

endmodule

src/data_memory.v
module data_memory(
    input wire clock,
    input wire MemRead, MemWrite,
    input wire [2:0] funct3,
    input wire [31:0] endereco,
    input wire [31:0] write_data,
    output wire [31:0] read_data
);
    reg [7:0] memoria [0:1023];
    reg [31:0] read_data_reg;

    // Inicializar memória com zeros para debug
    initial begin
        for (integer i = 0; i < 256; i = i + 1) begin
            memoria[i] = 32'b00000000;
        end
    end


    //leitura
    always @(*) begin
        if (MemRead) begin
            case (funct3)
                3'b010: begin // LW - Load Word (32-bit)
                    read_data_reg = {memoria[endereco+3], memoria[endereco+2], 
                               memoria[endereco+1], memoria[endereco]};
                end
                3'b001: begin // LH - Load Halfword unsigned (16-bit)
                    read_data_reg = {16'b0, memoria[endereco+1], memoria[endereco]};
                    //$display("DEBUG: LH endereco=%0d, dados=%b", endereco, {memoria[endereco+1], memoria[endereco]});
                end
                3'b000: begin // LB - Load Byte unsigned (8-bit) 
                    read_data_reg = {24'b0, memoria[endereco]};
                end
                default: begin
                    read_data_reg = 32'b0;
                end
            endcase
        end else begin
            read_data_reg = 32'b0; // Se não for leitura, retorna zero
        end
    end

    assign read_data = read_data_reg;

     always @(posedge clock) begin
        if (MemWrite) begin
            case (funct3)
                3'b010: begin // SW - Store Word (32-bit)
                    memoria[endereco]   <= write_data[7:0];
                    memoria[endereco+1] <= write_data[15:8];
                    memoria[endereco+2] <= write_data[23:16];
                    memoria[endereco+3] <= write_data[31:24];
                    //$display("DEBUG: SW endereco=%0d, dados=%h", endereco, write_data);
                end
                3'b001: begin // SH - Store Halfword (16-bit)
                    memoria[endereco]   <= write_data[7:0];
                    memoria[endereco+1] <= write_data[15:8];
                   // $display("DEBUG: SH endereco=%0d, dados=%b", endereco, write_data[15:0]);
                end
                3'b000: begin // SB - Store Byte (8-bit)
                    memoria[endereco] <= write_data[7:0];
                    //$display("DEBUG: SB endereco=%0d, dados=%h", endereco, write_data[7:0]);
                end
                default: begin
                    $display("DEBUG: Operação de store desconhecida funct3=%b", funct3);
                end
            endcase
        end
    end

endmodule

src/alu.v
module alu(
    input wire [31:0] entrada1,
    input wire [31:0] entrada2,
    input wire [3:0] alu_control,
    output reg [31:0] resultado,
    output wire zero
);

    assign zero = (resultado == 32'b0);
    always @(*) begin
        case (alu_control)
           4'b0010: resultado = entrada1 + entrada2;                // ADD
            4'b0110: resultado = entrada1 - entrada2;                // SUB
            4'b0000: resultado = entrada1 & entrada2;                // AND
            4'b0001: resultado = entrada1 | entrada2;                // OR
            4'b0100: resultado = entrada1 ^ entrada2;                // XOR
            4'b0101: resultado = ~(entrada1 | entrada2);             // NOR
            4'b0111: resultado = ($signed(entrada1) < $signed(entrada2)) ? 32'd1 : 32'd0; // SLT (se quiser)
            4'b1000: resultado = entrada1 << entrada2[4:0];          // SLL
            4'b1001: resultado = entrada1 >> entrada2[4:0];          // SRL
            default: resultado = 32'b0;
        endcase
    end

endmodule

src/alu_control.v
module alu_control(
    input  wire [1:0] ALUOp,      // vem do control unit
    input  wire [2:0] funct3,     // instrução
    input  wire [6:0] funct7,     // instrução (usamos bit[5] para distinguir SRL/SRA e ADD/SUB)
    output reg  [3:0] alu_control // código para a ALU
);

    always @(*) begin
        // default
        alu_control = 4'b0000; // ADD por padrão

        case (ALUOp)
            2'b00: begin
                // ALUOp=00: Para loads, stores, e instruções I-type imediatas
                // NOTA: funct3=010 em loads/stores deve usar ADD, não SLT!
                case (funct3)
                    3'b000: alu_control = 4'b0000; // ADD / ADDI / LW / SW
                    3'b001: alu_control = 4'b1000; // SLLI
                    3'b010: alu_control = 4'b0000; // LW/SW (usa ADD) / SLTI - CORRIGIDO!
                    3'b011: alu_control = 4'b0111; // SLTIU (unsigned)
                    3'b100: alu_control = 4'b0100; // XORI
                    3'b101: begin                   // SRLI / SRAI (depende de funct7[5])
                        if (funct7[5]) alu_control = 4'b1010; // SRAI
                        else           alu_control = 4'b1001; // SRLI
                    end
                    3'b110: alu_control = 4'b0011; // ORI
                    3'b111: alu_control = 4'b0010; // ANDI
                    default: alu_control = 4'b0000;
                endcase
            end

            2'b01: begin
                // Branches — normalmente comparam usando SUB (BEQ/BNE) e outros sinais externos interpretam resultado
                alu_control = 4'b0001; // SUB
            end

            2'b10: begin
                // R-type: usar funct3 e funct7
                case (funct3)
                    3'b000: begin
                        // ADD or SUB (funct7 = 0100000 indica SUB em RV32)
                        if (funct7 == 7'b0100000) alu_control = 4'b0001; // SUB
                        else                      alu_control = 4'b0000; // ADD
                    end
                    3'b001: alu_control = 4'b1000; // SLL
                    3'b010: alu_control = 4'b0110; // SLT (signed)
                    3'b011: alu_control = 4'b0111; // SLTU (unsigned)
                    3'b100: alu_control = 4'b0100; // XOR
                    3'b101: begin
                        // SRL or SRA (funct7[5] == 1 -> SRA)
                        if (funct7[5]) alu_control = 4'b1010; // SRA
                        else           alu_control = 4'b1001; // SRL
                    end
                    3'b110: alu_control = 4'b0011; // OR
                    3'b111: alu_control = 4'b0010; // AND
                    default: alu_control = 4'b0000;
                endcase
            end

            default: begin
                // segurança: ADD por padrão
                alu_control = 4'b0000;
            end
        endcase
    end

endmodule

src/imm_gen.v
module imm_gen (
    input  wire [31:0] instrucao,
    output reg  [31:0] imm_out
);

    wire [6:0] opcode = instrucao[6:0];

    always @(*) begin
        case (opcode)
            // I-type (ex.: addi, lw, jalr)
            7'b0000011, // LW
            7'b0010011, // ADDI
            7'b1100111: // JALR
                imm_out = {{20{instrucao[31]}}, instrucao[31:20]};

            // S-type (ex.: sw)
            7'b0100011:
                imm_out = {{20{instrucao[31]}}, instrucao[31:25], instrucao[11:7]};

            // B-type (ex.: beq, bne) - CORRIGIDO
            7'b1100011:
                imm_out = {{19{instrucao[31]}}, instrucao[31], instrucao[7],
                           instrucao[30:25], instrucao[11:8], 1'b0};

            // U-type (ex.: lui, auipc)
            7'b0110111, // LUI
            7'b0010111: // AUIPC
                imm_out = {instrucao[31:12], 12'b0};

            // J-type (ex.: jal)
            7'b1101111:
                imm_out = {{11{instrucao[31]}}, instrucao[31],
                           instrucao[19:12], instrucao[20],
                           instrucao[30:21], 1'b0};

            // Default (R-type ou instrução inválida)
            default:
                imm_out = 32'b0;
        endcase
    end

endmodule

src/register.v
module register(
    input logic clock,
    input logic RegWrite,
    input logic [4:0] rs1, rs2, rd,
    input logic [31:0] write_data,
    output logic [31:0] read_data1, read_data2
);
    reg [31:0] registradores [0:31];

    integer i;
    initial begin
        for (i = 0; i < 32; i = i + 1)
            registradores[i] = 32'b0;
    end

    assign read_data1 = (rs1 == 5'd0) ? 32'b0 : registradores[rs1];
    assign read_data2 = (rs2 == 5'd0) ? 32'b0 : registradores[rs2];

    always_ff @(posedge clock) begin
        if (RegWrite && rd != 5'd0) begin
            registradores[rd] <= write_data;
        end
    end

endmodule

src/control.v
module control(
    input wire [6:0] opcode,
    output reg Branch, MemRead, MemtoReg, MemWrite, ALUSrc, RegWrite,
    output logic [1:0] ALUOp    
);

    always @(*) begin
        Branch = 1'b0;
        MemRead = 1'b0;
        MemtoReg = 1'b0;
        MemWrite = 1'b0;
        ALUSrc = 1'b0;
        RegWrite = 1'b0;
        ALUOp = 2'b00;
        
        case(opcode)
            7'b0110011: begin // R-type
                RegWrite = 1'b1;
                ALUOp = 2'b10;
                ALUSrc = 1'b0;
                MemtoReg = 1'b0;
            end
            7'b0000011: begin // Load
                MemRead = 1'b1;
                MemtoReg = 1'b1;
                RegWrite = 1'b1;
                ALUSrc = 1'b1;
                ALUOp = 2'b00;
            end
            7'b0100011: begin // Store
                MemWrite = 1'b1;
                ALUSrc = 1'b1;
                ALUOp = 2'b00;
            end
            7'b1100011: begin // Branch
                Branch = 1'b1;
                ALUOp = 2'b01;
                ALUSrc = 1'b0;
            end
           default: begin
           end
        endcase
    end

endmodule

src/instruction_memory.v
module instruction_memory(
    input wire [31:0]endereco,
    output wire [31:0] instrucao
);
    reg [31:0] memoria [0:12];

    integer i;
    initial begin
         // Carregar programa
        $readmemb("entrada.bin", memoria, 0, 12);
        
        // Debug: mostrar instruções carregadas
        $display("=== INSTRUÇÕES CARREGADAS ===");
        for (i = 0; i < 13; i = i + 1) begin
            $display("memoria[%0d] = %b", i, memoria[i]);
        end
    end

    assign instrucao = memoria[endereco[9:2]];
endmodule

src/pc.v
module pc(
    input wire clock,
    input wire reset, pc_write,
    input wire [31:0] pc_prox, 
    output reg [31:0] pc
);

    always @(posedge clock or posedge reset) begin
        if (reset)
            pc <= 0;
        else if (pc_write)
            pc <= pc_prox;
    end

endmodule

src/cpu.v
module cpu (
    input wire clock,
    input wire reset
);

    // PC e Instrução
    wire [31:0] pc, pc_prox, pc_plus4;
    wire [31:0] instrucao;
    wire pc_write;

    assign pc_plus4 = pc + 32'd4;

    pc pc_reg(
        .clock(clock),
        .reset(reset),
        .pc_prox(pc_prox),
        .pc(pc),
        .pc_write(pc_write)
    );

    instruction_memory InstMem (
        .endereco(pc),
        .instrucao(instrucao)
    );

    // Decodificação
    wire [6:0] opcode = instrucao[6:0];
    wire [4:0] rd     = instrucao[11:7];
    wire [2:0] funct3 = instrucao[14:12];
    wire [4:0] rs1    = instrucao[19:15];
    wire [4:0] rs2    = instrucao[24:20];
    wire [6:0] funct7 = instrucao[31:25];

    // Registradores da instrução anterior (pipeline simples de 1 estágio)
    reg [4:0] prev_rd;
    reg prev_RegWrite;
    reg stall_cycle;

    wire [31:0] read_data1, read_data2;
    wire [31:0] immediate;

    wire Branch, MemRead, MemWrite, ALUSrc, RegWrite;
    wire MemtoReg;
    wire [1:0] ALUOp; 
    
    // Detecção de hazard simplificada - só 1 ciclo de stall
    wire raw_hazard = prev_RegWrite && prev_rd != 5'b0 && 
                      ((prev_rd == rs1 && rs1 != 5'b0) || 
                       (prev_rd == rs2 && rs2 != 5'b0));
    
    // Se há hazard, insere um stall
    assign pc_write = ~raw_hazard;
    
    // Durante stall, desabilita TODOS os controles de escrita
    wire RegWrite_safe = RegWrite & ~raw_hazard;
    wire MemWrite_safe = MemWrite & ~raw_hazard;

    control ctrl(
        .opcode(opcode),
        .Branch(Branch),
        .MemRead(MemRead),
        .MemtoReg(MemtoReg),
        .MemWrite(MemWrite),
        .ALUSrc(ALUSrc),
        .RegWrite(RegWrite),
        .ALUOp(ALUOp)
    );

    register registradores(
        .clock(clock),
        .RegWrite(RegWrite_safe),
        .rs1(rs1),
        .rs2(rs2),
        .rd(rd),
        .write_data(write_back_data),
        .read_data1(read_data1),
        .read_data2(read_data2)
    );

    imm_gen immGen(
        .instrucao(instrucao),
        .imm_out(immediate)
    );

    // ALU
    wire [3:0] alu_control;
    wire [31:0] alu_entrada2 = ALUSrc ? immediate : read_data2;
    wire [31:0] alu_result;
    wire zero;

    alu_control aluCtrl(
        .ALUOp(ALUOp),
        .funct3(funct3),
        .funct7(funct7),
        .alu_control(alu_control)
    );

    alu alu(
        .entrada1(read_data1),
        .entrada2(alu_entrada2),
        .alu_control(alu_control),
        .resultado(alu_result),
        .zero(zero)
    );

    // Memória de Dados
    wire [31:0] MemRead_data;

    data_memory dataMem(
        .clock(clock),
        .MemRead(MemRead),
        .MemWrite(MemWrite_safe),
        .endereco(alu_result),
        .write_data(read_data2),
        .read_data(MemRead_data)
    );

    // Write Back
    wire [31:0] write_back_data;

    mux2 #(.WIDTH(32)) write_back_mux(
        .seletor(MemtoReg),
        .entrada1(alu_result),
        .entrada2(MemRead_data),
        .saida(write_back_data)
    );

    // Controle de Desvio (Branch)
    wire [31:0] branch_alvo = pc + immediate;
    wire branch_taken = Branch & zero;

    mux2 #(.WIDTH(32)) pc_mux(
        .seletor(branch_taken),
        .entrada1(pc_plus4),
        .entrada2(branch_alvo),
        .saida(pc_prox)
    );
    
    // Pipeline tracking corrigido
    always @(posedge clock or posedge reset) begin
        if (reset) begin
            prev_rd <= 5'b0;
            prev_RegWrite <= 1'b0;
            stall_cycle <= 1'b0;
        end else begin
            // Sempre atualiza, mas durante stall desabilita prev_RegWrite
            // para que no próximo ciclo não detecte hazard novamente
            if (raw_hazard) begin
                // Durante stall, mantém prev_rd mas desabilita prev_RegWrite
                prev_RegWrite <= 1'b0;
                stall_cycle <= 1'b1;
            end else begin
                // Operação normal
                prev_rd <= rd;
                prev_RegWrite <= RegWrite;
                stall_cycle <= 1'b0;
            end
        end
    end

endmodule

src/testbench.v
`timescale 1ns/1ps

module testbench_simple;
    reg clock, reset;
    integer cycle_count;
    integer i;
    integer j;
    integer errors;

    cpu uut (
        .clock(clock),
        .reset(reset)
    );

    initial begin
        $dumpfile("simple_hazard.vcd");
        $dumpvars(0, uut);

        clock = 0;
        reset = 1;
        cycle_count = 0;

        #10;
        reset = 0;

        
        $display("\n=== REGISTRADORES INICIAIS ===");
        for (i = 0; i < 32; i = i + 1) begin
            $display("Register [ x%0d ]: %0d", i, uut.registradores.registradores[i]);
        end

        $display("\n=== DATA MEMORY INICIAIS ===");
        for (j = 0; j < 32; j = j + 1) begin
            $display("Memory [ x%0d ]: %0d", j, uut.dataMem.memoria[j]);
        end

        // Executar por mais ciclos
        #500;

        $display("\n=== RESULTADO FINAL ===");

        for (i = 0; i < 32; i = i + 1) begin
            $display("Register [ x%0d ]: %0d", i, uut.registradores.registradores[i]);
        end

        $display("\n=== DATA MEMORY FINAIS ===");
        for (j = 0; j < 32; j = j + 1) begin
            $display("Memory [ x%0d ]: %0d", j, uut.dataMem.memoria[j]);
        end

        $finish;
    end

    // Monitor com informações de hazard E DEBUG DE PATH DE DADOS
    /*always @(posedge clock) begin
        if (!reset) begin
            cycle_count = cycle_count + 1;
            
            if (cycle_count <= 20) begin // Mais ciclos para ver stalls
                $display("\n=== Ciclo %0d ===", cycle_count);
                
                if (uut.pc_write) begin
                    $display("PC=%0d → Instr: %b", uut.pc, uut.instrucao);
                    $display("Decodificado: rd=%0d, rs1=%0d, rs2=%0d, funct3=%b", 
                            uut.rd, uut.rs1, uut.rs2, uut.funct3);
                    $display("read_data1=%0d (x%0d), read_data2=%0d (x%0d)", 
                            uut.read_data1, uut.rs1, uut.read_data2, uut.rs2);
                    $display("prev_rd=%0d, prev_RegWrite=%b", uut.prev_rd, uut.prev_RegWrite);
                    
                    // DEBUG DO PATH DE DADOS
                    $display("--- DEBUG PATH DE DADOS ---");
                    $display("MemRead=%b, MemWrite=%b, MemtoReg=%b", 
                            uut.MemRead, uut.MemWrite, uut.MemtoReg);
                    $display("alu_result=%0d, MemRead_data=%0d", 
                            uut.alu_result, uut.MemRead_data);
                    $display("write_back_data=%0d (ALU=%0d, MEM=%0d)", 
                            uut.write_back_data, uut.alu_result, uut.MemRead_data);
                            
                end else begin
                    $display("⏸️  STALL: PC=%0d (hazard detectado)", uut.pc);
                    $display("   prev_rd=%0d conflita com rs1=%0d ou rs2=%0d", 
                            uut.prev_rd, uut.rs1, uut.rs2);
                    $display("   raw_hazard=%b (rs1_hazard=%b, rs2_hazard=%b)", 
                            uut.raw_hazard,
                            (uut.prev_RegWrite && uut.prev_rd != 5'b0 && uut.prev_rd == uut.rs1 && uut.rs1 != 5'b0),
                            (uut.prev_RegWrite && uut.prev_rd != 5'b0 && uut.prev_rd == uut.rs2 && uut.rs2 != 5'b0));
                end
                
                if (uut.RegWrite_safe && uut.rd != 0) begin
                    $display("✅ Escrevendo x%0d = %0d", uut.rd, uut.write_back_data);
                end
            end
        end
    end*/

    always begin
        #5 clock = ~clock;
    end

endmodule

src/simple_hazard.vcd
$date
	Tue Aug 26 17:50:16 2025
$end
$version
	Icarus Verilog
$end
$timescale
	1ps
$end
$scope module testbench_simple $end
$scope module uut $end
$var wire 1 ! MemWrite_safe $end
$var wire 1 " RegWrite_safe $end
$var wire 1 # branch_taken $end
$var wire 1 $ clock $end
$var wire 1 % pc_write $end
$var wire 1 & raw_hazard $end
$var wire 1 ' reset $end
$var wire 1 ( zero $end
$var wire 32 ) write_back_data [31:0] $end
$var wire 5 * rs2 [4:0] $end
$var wire 5 + rs1 [4:0] $end
$var wire 32 , read_data2 [31:0] $end
$var wire 32 - read_data1 [31:0] $end
$var wire 5 . rd [4:0] $end
$var wire 32 / pc_prox [31:0] $end
$var wire 32 0 pc_plus4 [31:0] $end
$var wire 32 1 pc [31:0] $end
$var wire 7 2 opcode [6:0] $end
$var wire 32 3 instrucao [31:0] $end
$var wire 32 4 immediate [31:0] $end
$var wire 7 5 funct7 [6:0] $end
$var wire 3 6 funct3 [2:0] $end
$var wire 32 7 branch_alvo [31:0] $end
$var wire 32 8 alu_result [31:0] $end
$var wire 32 9 alu_entrada2 [31:0] $end
$var wire 4 : alu_control [3:0] $end
$var wire 1 ; RegWrite $end
$var wire 1 < MemtoReg $end
$var wire 1 = MemWrite $end
$var wire 32 > MemRead_data [31:0] $end
$var wire 1 ? MemRead $end
$var wire 1 @ Branch $end
$var wire 1 A ALUSrc $end
$var wire 2 B ALUOp [1:0] $end
$var reg 1 C prev_RegWrite $end
$var reg 5 D prev_rd [4:0] $end
$var reg 1 E stall_cycle $end
$scope module InstMem $end
$var wire 32 F instrucao [31:0] $end
$var wire 32 G endereco [31:0] $end
$var integer 32 H i [31:0] $end
$upscope $end
$scope module alu $end
$var wire 32 I entrada2 [31:0] $end
$var wire 1 ( zero $end
$var wire 32 J entrada1 [31:0] $end
$var wire 4 K alu_control [3:0] $end
$var reg 32 L resultado [31:0] $end
$upscope $end
$scope module aluCtrl $end
$var wire 3 M funct3 [2:0] $end
$var wire 7 N funct7 [6:0] $end
$var wire 2 O ALUOp [1:0] $end
$var reg 4 P alu_control [3:0] $end
$upscope $end
$scope module ctrl $end
$var wire 7 Q opcode [6:0] $end
$var reg 2 R ALUOp [1:0] $end
$var reg 1 A ALUSrc $end
$var reg 1 @ Branch $end
$var reg 1 ? MemRead $end
$var reg 1 = MemWrite $end
$var reg 1 < MemtoReg $end
$var reg 1 ; RegWrite $end
$upscope $end
$scope module dataMem $end
$var wire 1 S MemRead $end
$var wire 1 ! MemWrite $end
$var wire 1 $ clock $end
$var wire 32 T endereco [31:0] $end
$var wire 3 U funct3 [2:0] $end
$var wire 32 V write_data [31:0] $end
$var wire 32 W read_data [31:0] $end
$var reg 32 X read_data_reg [31:0] $end
$scope begin $ivl_for_loop0 $end
$var integer 32 Y i [31:0] $end
$upscope $end
$upscope $end
$scope module immGen $end
$var wire 32 Z instrucao [31:0] $end
$var wire 7 [ opcode [6:0] $end
$var reg 32 \ imm_out [31:0] $end
$upscope $end
$scope module pc_mux $end
$var wire 32 ] entrada1 [31:0] $end
$var wire 32 ^ entrada2 [31:0] $end
$var wire 1 # seletor $end
$var wire 32 _ saida [31:0] $end
$var parameter 32 ` WIDTH $end
$upscope $end
$scope module pc_reg $end
$var wire 1 $ clock $end
$var wire 32 a pc_prox [31:0] $end
$var wire 1 % pc_write $end
$var wire 1 ' reset $end
$var reg 32 b pc [31:0] $end
$upscope $end
$scope module registradores $end
$var wire 1 " RegWrite $end
$var wire 1 $ clock $end
$var wire 5 c rd [4:0] $end
$var wire 5 d rs1 [4:0] $end
$var wire 5 e rs2 [4:0] $end
$var wire 32 f write_data [31:0] $end
$var reg 32 g read_data1 [31:0] $end
$var reg 32 h read_data2 [31:0] $end
$var integer 32 i i [31:0] $end
$upscope $end
$scope module write_back_mux $end
$var wire 32 j entrada1 [31:0] $end
$var wire 32 k entrada2 [31:0] $end
$var wire 1 < seletor $end
$var wire 32 l saida [31:0] $end
$var parameter 32 m WIDTH $end
$upscope $end
$upscope $end
$upscope $end
$enddefinitions $end
$comment Show the parameter values. $end
$dumpall
b100000 m
b100000 `
$end
#0
$dumpvars
b1111 l
b0 k
b1111 j
b100000 i
b0 h
b0 g
b1111 f
b1111 e
b0 d
b10 c
b0 b
b100 a
b100 _
b1111 ^
b100 ]
b1111 \
b10011 [
b111100000000000100010011 Z
b100000000 Y
b0 X
b0 W
b0 V
b0 U
b1111 T
0S
b0 R
b10011 Q
b0 P
b0 O
b0 N
b0 M
b1111 L
b0 K
b0 J
b1111 I
b1101 H
b0 G
b111100000000000100010011 F
0E
b0 D
0C
b0 B
1A
0@
0?
b0 >
0=
0<
1;
b0 :
b1111 9
b1111 8
b1111 7
b0 6
b0 5
b1111 4
b111100000000000100010011 3
b10011 2
b0 1
b100 0
b100 /
b10 .
b0 -
b0 ,
b0 +
b1111 *
b1111 )
0(
1'
0&
1%
0$
0#
1"
0!
$end
#5000
1$
#10000
0$
0'
#15000
0%
b0 )
b0 f
b0 l
1&
1(
b0 8
b0 L
b0 T
b0 j
0!
0"
b0 9
b0 I
b1111 ,
b1111 V
b1111 h
1=
0;
1A
b0 4
b0 \
b100011 [
b10 *
b10 e
b1 6
b1 M
b1 U
b0 .
b0 c
b100011 2
b100011 Q
b1000000001000000100011 3
b1000000001000000100011 F
b1000000001000000100011 Z
b1000 /
b1000 _
b1000 a
b100 7
b100 ^
b1000 0
b1000 ]
b100 1
b100 G
b100 b
1C
b10 D
1$
#20000
0$
#25000
1!
1%
0&
1E
0C
1$
#30000
0$
#35000
b1100100 )
b1100100 f
b1100100 l
0(
b1100100 8
b1100100 L
b1100100 T
b1100100 j
1"
0!
b1100100 9
b1100100 I
b0 ,
b0 V
b0 h
1;
1A
0=
b1100100 4
b1100100 \
b10011 [
b11 5
b11 N
b100 *
b100 e
b0 6
b0 M
b0 U
b11 .
b11 c
b10011 2
b10011 Q
b110010000000000000110010011 3
b110010000000000000110010011 F
b110010000000000000110010011 Z
b1100 /
b1100 _
b1100 a
b1101100 7
b1101100 ^
b1100 0
b1100 ]
b1000 1
b1000 G
b1000 b
0E
b0 D
1$
#40000
0$
#45000
0%
b10 )
b10 f
b10 l
1&
b10 8
b10 L
b10 T
b10 j
0!
0"
b10 9
b10 I
b1100100 ,
b1100100 V
b1100100 h
1=
0;
1A
b10 4
b10 \
b100011 [
b0 5
b0 N
b11 *
b11 e
b1 6
b1 M
b1 U
b10 .
b10 c
b100011 2
b100011 Q
b1100000001000100100011 3
b1100000001000100100011 F
b1100000001000100100011 Z
b10000 /
b10000 _
b10000 a
1C
b11 D
b1110 7
b1110 ^
b10000 0
b10000 ]
b1100 1
b1100 G
b1100 b
1$
#50000
0$
#55000
1!
1%
0&
1E
0C
1$
#60000
0$
#65000
b1111 >
b1111 W
b1111 X
b1111 k
1(
b0 8
b0 L
b0 T
b0 j
b1111 )
b1111 f
b1111 l
1S
1"
0!
b0 9
b0 I
b0 ,
b0 V
b0 h
1<
1?
1;
1A
0=
b0 4
b0 \
b11 [
b0 *
b0 e
b100 .
b100 c
b11 2
b11 Q
b1001000000011 3
b1001000000011 F
b1001000000011 Z
b10100 /
b10100 _
b10100 a
0E
b10 D
b10000 7
b10000 ^
b10100 0
b10100 ]
b10000 1
b10000 G
b10000 b
1$
#70000
0$
#75000
b1100100 )
b1100100 f
b1100100 l
b1100100 >
b1100100 W
b1100100 X
b1100100 k
0(
b10 8
b10 L
b10 T
b10 j
b10 9
b10 I
b1111 ,
b1111 V
b1111 h
b10 4
b10 \
b10 *
b10 e
b101 .
b101 c
b1000000001001010000011 3
b1000000001001010000011 F
b1000000001001010000011 Z
b11000 /
b11000 _
b11000 a
b10110 7
b10110 ^
b11000 0
b11000 ]
b10100 1
b10100 G
b10100 b
1C
b100 D
1$
#80000
0$
#85000
0"
0%
1&
b0 >
b0 W
b0 X
b0 k
b1010101 8
b1010101 L
b1010101 T
b1010101 j
b1010101 )
b1010101 f
b1010101 l
0S
b1111 9
b1111 I
b1100100 -
b1100100 J
b1100100 g
b1 :
b1 K
b1 P
b10 B
b10 O
b10 R
0<
1;
0A
0?
b0 4
b0 \
b110011 [
b100000 5
b100000 N
b100 *
b100 e
b101 +
b101 d
b0 6
b0 M
b0 U
b110 .
b110 c
b110011 2
b110011 Q
b1000000010000101000001100110011 3
b1000000010000101000001100110011 F
b1000000010000101000001100110011 Z
b11100 /
b11100 _
b11100 a
b101 D
b11000 7
b11000 ^
b11100 0
b11100 ]
b11000 1
b11000 G
b11000 b
1$
#90000
0$
#95000
1"
1%
0&
1E
0C
1$
#100000
0$
#105000
b1101111 )
b1101111 f
b1101111 l
b1101111 8
b1101111 L
b1101111 T
b1101111 j
b11 :
b11 K
b11 P
b0 5
b0 N
b110 6
b110 M
b110 U
b111 .
b111 c
b10000101110001110110011 3
b10000101110001110110011 F
b10000101110001110110011 Z
b100000 /
b100000 _
b100000 a
0E
1C
b110 D
b11100 7
b11100 ^
b100000 0
b100000 ]
b11100 1
b11100 G
b11100 b
1$
#110000
0$
#115000
b101 )
b101 f
b101 l
b101 8
b101 L
b101 T
b101 j
b0 ,
b0 V
b0 h
b1010101 -
b1010101 J
b1010101 g
b10 :
b10 K
b10 P
1A
b0 B
b0 O
b0 R
1;
b1111 4
b1111 \
b10011 [
b1111 *
b1111 e
b110 +
b110 d
b111 6
b111 M
b111 U
b1000 .
b1000 c
b10011 2
b10011 Q
b111100110111010000010011 3
b111100110111010000010011 F
b111100110111010000010011 Z
b100100 /
b100100 _
b100100 a
b101111 7
b101111 ^
b100100 0
b100100 ]
b100000 1
b100000 G
b100000 b
b111 D
1$
#120000
0$
#125000
b0 )
b0 f
b0 l
1(
b0 8
b0 L
b0 T
b0 j
b1111 ,
b1111 V
b1111 h
b1101111 -
b1101111 J
b1101111 g
b1001 :
b1001 K
b1001 P
b10 B
b10 O
b10 R
1;
0A
b0 4
b0 \
b110011 [
b100 *
b100 e
b111 +
b111 d
b101 6
b101 M
b101 U
b1001 .
b1001 c
b110011 2
b110011 Q
b10000111101010010110011 3
b10000111101010010110011 F
b10000111101010010110011 Z
b101000 /
b101000 _
b101000 a
b1000 D
b100100 7
b100100 ^
b101000 0
b101000 ]
b100100 1
b100100 G
b100100 b
1$
#130000
0$
#135000
b11111111111111111111111110101011 )
b11111111111111111111111110101011 f
b11111111111111111111111110101011 l
0(
b11111111111111111111111110101011 8
b11111111111111111111111110101011 L
b11111111111111111111111110101011 T
b11111111111111111111111110101011 j
b1100100 9
b1100100 I
0#
0"
b1100100 ,
b1100100 V
b1100100 h
b1111 -
b1111 J
b1111 g
b1 :
b1 K
b1 P
1@
b1 B
b1 O
b1 R
0;
b1000 4
b1000 \
b1100011 [
b101 *
b101 e
b100 +
b100 d
b0 6
b0 M
b0 U
b1000 .
b1000 c
b1100011 2
b1100011 Q
b10100100000010001100011 3
b10100100000010001100011 F
b10100100000010001100011 Z
b101100 /
b101100 _
b101100 a
b110000 7
b110000 ^
b101100 0
b101100 ]
b101000 1
b101000 G
b101000 b
b1001 D
1$
#140000
0$
#145000
b1 )
b1 f
b1 l
b1 8
b1 L
b1 T
b1 j
b1 9
b1 I
1"
b0 :
b0 K
b0 P
b0 ,
b0 V
b0 h
b0 -
b0 J
b0 g
1A
1;
b0 B
b0 O
b0 R
0@
b1 4
b1 \
b10011 [
b1 *
b1 e
b0 +
b0 d
b1010 .
b1010 c
b10011 2
b10011 Q
b100000000010100010011 3
b100000000010100010011 F
b100000000010100010011 Z
b110000 /
b110000 _
b110000 a
0C
b1000 D
b101101 7
b101101 ^
b110000 0
b110000 ]
b101100 1
b101100 G
b101100 b
1$
#150000
0$
#155000
b0 )
b0 f
b0 l
1(
b0 8
b0 L
b0 T
b0 j
b0 9
b0 I
b0 4
b0 \
b0 *
b0 e
b0 .
b0 c
b10011 3
b10011 F
b10011 Z
b110100 /
b110100 _
b110100 a
b110000 7
b110000 ^
b110100 0
b110100 ]
b110000 1
b110000 G
b110000 b
1C
b1010 D
1$
#160000
0$
#165000
bx )
bx f
bx l
x(
bx 8
bx L
bx T
bx j
0"
bx 9
bx I
bx ,
bx V
bx h
bx -
bx J
bx g
0;
0A
bx [
bx 5
bx N
bx *
bx e
bx +
bx d
bx 6
bx M
bx U
bx .
bx c
bx 2
bx Q
bx 3
bx F
bx Z
b111000 /
b111000 _
b111000 a
b0 D
b110100 7
b110100 ^
b111000 0
b111000 ]
b110100 1
b110100 G
b110100 b
1$
#170000
0$
#175000
b111100 /
b111100 _
b111100 a
b111000 7
b111000 ^
b111100 0
b111100 ]
b111000 1
b111000 G
b111000 b
0C
bx D
1$
#180000
0$
#185000
b1000000 /
b1000000 _
b1000000 a
b111100 7
b111100 ^
b1000000 0
b1000000 ]
b111100 1
b111100 G
b111100 b
1$
#190000
0$
#195000
b1000100 /
b1000100 _
b1000100 a
b1000000 7
b1000000 ^
b1000100 0
b1000100 ]
b1000000 1
b1000000 G
b1000000 b
1$
#200000
0$
#205000
b1001000 /
b1001000 _
b1001000 a
b1000100 7
b1000100 ^
b1001000 0
b1001000 ]
b1000100 1
b1000100 G
b1000100 b
1$
#210000
0$
#215000
b1001100 /
b1001100 _
b1001100 a
b1001000 7
b1001000 ^
b1001100 0
b1001100 ]
b1001000 1
b1001000 G
b1001000 b
1$
#220000
0$
#225000
b1010000 /
b1010000 _
b1010000 a
b1001100 7
b1001100 ^
b1010000 0
b1010000 ]
b1001100 1
b1001100 G
b1001100 b
1$
#230000
0$
#235000
b1010100 /
b1010100 _
b1010100 a
b1010000 7
b1010000 ^
b1010100 0
b1010100 ]
b1010000 1
b1010000 G
b1010000 b
1$
#240000
0$
#245000
b1011000 /
b1011000 _
b1011000 a
b1010100 7
b1010100 ^
b1011000 0
b1011000 ]
b1010100 1
b1010100 G
b1010100 b
1$
#250000
0$
#255000
b1011100 /
b1011100 _
b1011100 a
b1011000 7
b1011000 ^
b1011100 0
b1011100 ]
b1011000 1
b1011000 G
b1011000 b
1$
#260000
0$
