src/mux2.v
module mux2 #(parameter WIDTH = 32)(
    input wire seletor,
    input wire [WIDTH-1:0] entrada1,
    input wire [WIDTH-1:0] entrada2,
    output wire [WIDTH-1:0] saida
);
    assign saida = (seletor) ? entrada2 : entrada1;

endmodule

src/data_memory.v
module data_memory(
    input wire clock,
    input wire MemRead, MemWrite,
    input wire [2:0] funct3,
    input wire [31:0] endereco,
    input wire [31:0] write_data,
    output wire [31:0] read_data
);
    reg [7:0] memoria [0:1023];
    reg [31:0] read_data_reg;

    // Inicializar memória com zeros para debug
    initial begin
        for (integer i = 0; i < 256; i = i + 1) begin
            memoria[i] = 32'b00000000;
        end
    end


    //leitura
    always @(posedge clock) begin
        if (MemRead) begin
            case (funct3)
                3'b010: begin // LW - Load Word (32-bit)
                    read_data_reg = {memoria[endereco+3], memoria[endereco+2], 
                               memoria[endereco+1], memoria[endereco]};
                end
                3'b001: begin // LH - Load Halfword unsigned (16-bit)
                    read_data_reg = {16'b0, memoria[endereco+1], memoria[endereco]};
                    $display("DEBUG: LH endereco=%0d, dados=%b", endereco, {memoria[endereco+1], memoria[endereco]});
                end
                3'b000: begin // LB - Load Byte unsigned (8-bit) 
                    read_data_reg = {24'b0, memoria[endereco]};
                end
                default: begin
                    read_data_reg = 32'b0;
                end
            endcase
        end else begin
            read_data_reg = 32'b0; // Se não for leitura, retorna zero
        end
    end

    assign read_data = read_data_reg;

     always @(posedge clock) begin
        if (MemWrite) begin
            case (funct3)
                3'b010: begin // SW - Store Word (32-bit)
                    memoria[endereco]   <= write_data[7:0];
                    memoria[endereco+1] <= write_data[15:8];
                    memoria[endereco+2] <= write_data[23:16];
                    memoria[endereco+3] <= write_data[31:24];
                    $display("DEBUG: SW endereco=%0d, dados=%h", endereco, write_data);
                end
                3'b001: begin // SH - Store Halfword (16-bit)
                    memoria[endereco]   <= write_data[7:0];
                    memoria[endereco+1] <= write_data[15:8];
                    $display("DEBUG: SH endereco=%0d, dados=%b", endereco, write_data[15:0]);
                end
                3'b000: begin // SB - Store Byte (8-bit)
                    memoria[endereco] <= write_data[7:0];
                    $display("DEBUG: SB endereco=%0d, dados=%h", endereco, write_data[7:0]);
                end
                default: begin
                    $display("DEBUG: Operação de store desconhecida funct3=%b", funct3);
                end
            endcase
        end
    end

endmodule

src/alu.v
module alu(
    input wire [31:0] entrada1,
    input wire [31:0] entrada2,
    input wire [3:0] alu_control,
    output reg [31:0] resultado,
    output wire zero
);

    assign zero = (resultado == 32'b0);
    always @(*) begin
        case (alu_control)
           4'b0010: resultado = entrada1 + entrada2;                // ADD
            4'b0110: resultado = entrada1 - entrada2;                // SUB
            4'b0000: resultado = entrada1 & entrada2;                // AND
            4'b0001: resultado = entrada1 | entrada2;                // OR
            4'b0100: resultado = entrada1 ^ entrada2;                // XOR
            4'b0101: resultado = ~(entrada1 | entrada2);             // NOR
            4'b0111: resultado = ($signed(entrada1) < $signed(entrada2)) ? 32'd1 : 32'd0; // SLT (se quiser)
            4'b1000: resultado = entrada1 << entrada2[4:0];          // SLL
            4'b1001: resultado = entrada1 >> entrada2[4:0];          // SRL
            default: resultado = 32'b0;
        endcase
    end

endmodule

src/alu_control.v
module alu_control(
    input  wire [1:0] ALUOp,      // vem do control unit
    input  wire [2:0] funct3,     // instrução
    input  wire [6:0] funct7,     // instrução (usamos bit[5] para distinguir SRL/SRA e ADD/SUB)
    output reg  [3:0] alu_control // código para a ALU
);

    always @(*) begin
        // default
        alu_control = 4'b0000; // ADD por padrão

        case (ALUOp)
            2'b00: begin
                // ALUOp=00: Para loads, stores, e instruções I-type imediatas
                // NOTA: funct3=010 em loads/stores deve usar ADD, não SLT!
                case (funct3)
                    3'b000: alu_control = 4'b0000; // ADD / ADDI / LW / SW
                    3'b001: alu_control = 4'b1000; // SLLI
                    3'b010: alu_control = 4'b0000; // LW/SW (usa ADD) / SLTI - CORRIGIDO!
                    3'b011: alu_control = 4'b0111; // SLTIU (unsigned)
                    3'b100: alu_control = 4'b0100; // XORI
                    3'b101: begin                   // SRLI / SRAI (depende de funct7[5])
                        if (funct7[5]) alu_control = 4'b1010; // SRAI
                        else           alu_control = 4'b1001; // SRLI
                    end
                    3'b110: alu_control = 4'b0011; // ORI
                    3'b111: alu_control = 4'b0010; // ANDI
                    default: alu_control = 4'b0000;
                endcase
            end

            2'b01: begin
                // Branches — normalmente comparam usando SUB (BEQ/BNE) e outros sinais externos interpretam resultado
                alu_control = 4'b0001; // SUB
            end

            2'b10: begin
                // R-type: usar funct3 e funct7
                case (funct3)
                    3'b000: begin
                        // ADD or SUB (funct7 = 0100000 indica SUB em RV32)
                        if (funct7 == 7'b0100000) alu_control = 4'b0001; // SUB
                        else                      alu_control = 4'b0000; // ADD
                    end
                    3'b001: alu_control = 4'b1000; // SLL
                    3'b010: alu_control = 4'b0110; // SLT (signed)
                    3'b011: alu_control = 4'b0111; // SLTU (unsigned)
                    3'b100: alu_control = 4'b0100; // XOR
                    3'b101: begin
                        // SRL or SRA (funct7[5] == 1 -> SRA)
                        if (funct7[5]) alu_control = 4'b1010; // SRA
                        else           alu_control = 4'b1001; // SRL
                    end
                    3'b110: alu_control = 4'b0011; // OR
                    3'b111: alu_control = 4'b0010; // AND
                    default: alu_control = 4'b0000;
                endcase
            end

            default: begin
                // segurança: ADD por padrão
                alu_control = 4'b0000;
            end
        endcase
    end

endmodule

src/imm_gen.v
module imm_gen (
    input  wire [31:0] instrucao,
    output reg  [31:0] imm_out
);

    wire [6:0] opcode = instrucao[6:0];

    always @(*) begin
        case (opcode)
            // I-type (ex.: addi, lw, jalr)
            7'b0000011, // LW
            7'b0010011, // ADDI
            7'b1100111: // JALR
                imm_out = {{20{instrucao[31]}}, instrucao[31:20]};

            // S-type (ex.: sw)
            7'b0100011:
                imm_out = {{20{instrucao[31]}}, instrucao[31:25], instrucao[11:7]};

            // B-type (ex.: beq, bne) - CORRIGIDO
            7'b1100011:
                imm_out = {{19{instrucao[31]}}, instrucao[31], instrucao[7],
                           instrucao[30:25], instrucao[11:8], 1'b0};

            // U-type (ex.: lui, auipc)
            7'b0110111, // LUI
            7'b0010111: // AUIPC
                imm_out = {instrucao[31:12], 12'b0};

            // J-type (ex.: jal)
            7'b1101111:
                imm_out = {{11{instrucao[31]}}, instrucao[31],
                           instrucao[19:12], instrucao[20],
                           instrucao[30:21], 1'b0};

            // Default (R-type ou instrução inválida)
            default:
                imm_out = 32'b0;
        endcase
    end

endmodule

src/register.v
module register(
    input logic clock,
    input logic RegWrite,
    input logic [4:0] rs1, rs2, rd,
    input logic [31:0] write_data,
    output logic [31:0] read_data1, read_data2
);
    reg [31:0] registradores [0:31];

    integer i;
    initial begin
        for (i = 0; i < 32; i = i + 1)
            registradores[i] = 32'b0;
    end

    assign read_data1 = (rs1 == 5'd0) ? 32'b0 : registradores[rs1];
    assign read_data2 = (rs2 == 5'd0) ? 32'b0 : registradores[rs2];

    always_ff @(posedge clock) begin
        if (RegWrite && rd != 5'd0) begin
            registradores[rd] <= write_data;
        end
    end

endmodule

src/control.v
module control(
    input wire [6:0] opcode,
    output reg Branch, MemRead, MemtoReg, MemWrite, ALUSrc, RegWrite,
    output logic [1:0] ALUOp    
);

    always @(*) begin
        Branch = 1'b0;
        MemRead = 1'b0;
        MemtoReg = 1'b0;
        MemWrite = 1'b0;
        ALUSrc = 1'b0;
        RegWrite = 1'b0;
        ALUOp = 2'b00;
        
        case(opcode)
            7'b0110011: begin // R-type
                RegWrite = 1'b1;
                ALUOp = 2'b10;
                ALUSrc = 1'b0;
                MemtoReg = 1'b0;
            end
            7'b0000011: begin // Load
                MemRead = 1'b1;
                MemtoReg = 1'b1;
                RegWrite = 1'b1;
                ALUSrc = 1'b1;
                ALUOp = 2'b00;
            end
            7'b0100011: begin // Store
                MemWrite = 1'b1;
                ALUSrc = 1'b1;
                ALUOp = 2'b00;
            end
            7'b1100011: begin // Branch
                Branch = 1'b1;
                ALUOp = 2'b01;
                ALUSrc = 1'b0;
            end
           default: begin
           end
        endcase
    end

endmodule

src/instruction_memory.v
module instruction_memory(
    input wire [31:0]endereco,
    output wire [31:0] instrucao
);
    reg [31:0] memoria [0:12];

    integer i;
    initial begin
         // Carregar programa
        $readmemb("programa.bin", memoria, 0, 12);
        
        // Debug: mostrar instruções carregadas
        $display("=== INSTRUÇÕES CARREGADAS ===");
        for (i = 0; i < 15; i = i + 1) begin
            $display("memoria[%0d] = %b", i, memoria[i]);
        end
    end

    assign instrucao = memoria[endereco[9:2]];
endmodule

src/pc.v
module pc(
    input wire clock,
    input wire reset, pc_write,
    input wire [31:0] pc_prox, 
    output reg [31:0] pc
);

    always @(posedge clock or posedge reset) begin
        if (reset)
            pc <= 0;
        else if (pc_write)
            pc <= pc_prox;
    end

endmodule

src/cpu.v
module cpu (
    input wire clock,
    input wire reset
);

    // PC e Instrução
    wire [31:0] pc, pc_prox, pc_plus4;
    wire [31:0] instrucao;
    wire pc_write;

    assign pc_plus4 = pc + 32'd4;

    pc pc_reg(
        .clock(clock),
        .reset(reset),
        .pc_prox(pc_prox),
        .pc(pc),
        .pc_write(pc_write)
    );

    instruction_memory InstMem (
        .endereco(pc),
        .instrucao(instrucao)
    );

    // Decodificação
    wire [6:0] opcode = instrucao[6:0];
    wire [4:0] rd     = instrucao[11:7];
    wire [2:0] funct3 = instrucao[14:12];
    wire [4:0] rs1    = instrucao[19:15];
    wire [4:0] rs2    = instrucao[24:20];
    wire [6:0] funct7 = instrucao[31:25];

    // Registradores da instrução anterior (pipeline simples de 1 estágio)
    reg [4:0] prev_rd;
    reg prev_RegWrite;
    reg stall_cycle;

    wire [31:0] read_data1, read_data2;
    wire [31:0] immediate;

    wire Branch, MemRead, MemWrite, ALUSrc, RegWrite;
    wire MemtoReg;
    wire [1:0] ALUOp; 
    
    // Detecção de hazard simplificada - só 1 ciclo de stall
    wire raw_hazard = prev_RegWrite && prev_rd != 5'b0 && 
                      ((prev_rd == rs1 && rs1 != 5'b0) || 
                       (prev_rd == rs2 && rs2 != 5'b0));
    
    // Se há hazard, insere um stall
    assign pc_write = ~raw_hazard;
    
    // Durante stall, desabilita TODOS os controles de escrita
    wire RegWrite_safe = RegWrite & ~raw_hazard;
    wire MemWrite_safe = MemWrite & ~raw_hazard;

    control ctrl(
        .opcode(opcode),
        .Branch(Branch),
        .MemRead(MemRead),
        .MemtoReg(MemtoReg),
        .MemWrite(MemWrite),
        .ALUSrc(ALUSrc),
        .RegWrite(RegWrite),
        .ALUOp(ALUOp)
    );

    register registradores(
        .clock(clock),
        .RegWrite(RegWrite_safe),
        .rs1(rs1),
        .rs2(rs2),
        .rd(rd),
        .write_data(write_back_data),
        .read_data1(read_data1),
        .read_data2(read_data2)
    );

    imm_gen immGen(
        .instrucao(instrucao),
        .imm_out(immediate)
    );
    
    wire [31:0] read_data1_fwd = (prev_RegWrite && prev_rd != 5'b0 && prev_rd == rs1) ? write_back_data : read_data1;
    wire [31:0] read_data2_fwd = (prev_RegWrite && prev_rd != 5'b0 && prev_rd == rs2) ? write_back_data : read_data2;

    // ALU
    wire [3:0] alu_control;
    wire [31:0] alu_entrada2 = ALUSrc ? immediate : read_data2_fwd;
    wire [31:0] alu_result;
    wire zero;

    alu_control aluCtrl(
        .ALUOp(ALUOp),
        .funct3(funct3),
        .funct7(funct7),
        .alu_control(alu_control)
    );

    alu alu(
        .entrada1(read_data1_fwd),
        .entrada2(alu_entrada2),
        .alu_control(alu_control),
        .resultado(alu_result),
        .zero(zero)
    );

    // Memória de Dados
    wire [31:0] MemRead_data;

    data_memory dataMem(
        .clock(clock),
        .MemRead(MemRead & ~raw_hazard),
        .MemWrite(MemWrite_safe),
        .funct3(funct3),
        .endereco(alu_result),
        .write_data(read_data2),
        .read_data(MemRead_data)
    );

    // Write Back
    wire [31:0] write_back_data;

    mux2 #(.WIDTH(32)) write_back_mux(
        .seletor(MemtoReg),
        .entrada1(alu_result),
        .entrada2(MemRead_data),
        .saida(write_back_data)
    );

    // Controle de Desvio (Branch)
    wire [31:0] branch_alvo = pc + immediate;
    wire branch_taken = Branch & zero;

    mux2 #(.WIDTH(32)) pc_mux(
        .seletor(branch_taken),
        .entrada1(pc_plus4),
        .entrada2(branch_alvo),
        .saida(pc_prox)
    );
    
    // Pipeline tracking corrigido
    always @(posedge clock or posedge reset) begin
        if (reset) begin
            prev_rd <= 5'b0;
            prev_RegWrite <= 1'b0;
            stall_cycle <= 1'b0;
        end else begin
            // Sempre atualiza, mas durante stall desabilita prev_RegWrite
            // para que no próximo ciclo não detecte hazard novamente
            if (raw_hazard) begin
                // Durante stall, mantém prev_rd mas desabilita prev_RegWrite
                prev_RegWrite <= 1'b0;
                stall_cycle <= 1'b1;
            end else begin
                // Operação normal
                prev_rd <= rd;
                prev_RegWrite <= RegWrite;
                stall_cycle <= 1'b0;
            end
        end
    end

endmodule

src/testbench.v
`timescale 1ns/1ps

module testbench_simple;
    reg clock, reset;
    integer cycle_count;
    integer i;
    integer errors;

    cpu uut (
        .clock(clock),
        .reset(reset)
    );

    initial begin
        $dumpfile("simple_hazard.vcd");
        $dumpvars(0, uut);

        clock = 0;
        reset = 1;
        cycle_count = 0;

        #10;
        reset = 0;

        
        $display("\n=== REGISTRADORES INICIAIS ===");
        for (i = 0; i < 32; i = i + 1) begin
            $display("x%0d = %0d", i, uut.registradores.registradores[i]);
        end

        // Executar por mais ciclos
        #500;

        $display("\n=== RESULTADO FINAL ===");
        // Adicionado para mostrar os registradores no final
        for (i = 0; i < 32; i = i + 1) begin
            $display("Register [ x%0d ]: %0d", i, uut.registradores.registradores[i]);
        end

        $finish;
    end

    // Monitor com informações de hazard E DEBUG DE PATH DE DADOS
    always @(posedge clock) begin
        if (!reset) begin
            cycle_count = cycle_count + 1;
            
            if (cycle_count <= 20) begin // Mais ciclos para ver stalls
                $display("\n=== Ciclo %0d ===", cycle_count);
                
                if (uut.pc_write) begin
                    $display("PC=%0d → Instr: %b", uut.pc, uut.instrucao);
                    $display("Decodificado: rd=%0d, rs1=%0d, rs2=%0d, funct3=%b", 
                            uut.rd, uut.rs1, uut.rs2, uut.funct3);
                    $display("read_data1=%0d (x%0d), read_data2=%0d (x%0d)", 
                            uut.read_data1, uut.rs1, uut.read_data2, uut.rs2);
                    $display("prev_rd=%0d, prev_RegWrite=%b", uut.prev_rd, uut.prev_RegWrite);
                    
                    // DEBUG DO PATH DE DADOS
                    $display("--- DEBUG PATH DE DADOS ---");
                    $display("MemRead=%b, MemWrite=%b, MemtoReg=%b", 
                            uut.MemRead, uut.MemWrite, uut.MemtoReg);
                    $display("alu_result=%0d, MemRead_data=%0d", 
                            uut.alu_result, uut.MemRead_data);
                    $display("write_back_data=%0d (ALU=%0d, MEM=%0d)", 
                            uut.write_back_data, uut.alu_result, uut.MemRead_data);
                            
                end else begin
                    $display("⏸️  STALL: PC=%0d (hazard detectado)", uut.pc);
                    $display("   prev_rd=%0d conflita com rs1=%0d ou rs2=%0d", 
                            uut.prev_rd, uut.rs1, uut.rs2);
                    $display("   raw_hazard=%b (rs1_hazard=%b, rs2_hazard=%b)", 
                            uut.raw_hazard,
                            (uut.prev_RegWrite && uut.prev_rd != 5'b0 && uut.prev_rd == uut.rs1 && uut.rs1 != 5'b0),
                            (uut.prev_RegWrite && uut.prev_rd != 5'b0 && uut.prev_rd == uut.rs2 && uut.rs2 != 5'b0));
                end
                
                if (uut.RegWrite_safe && uut.rd != 0) begin
                    $display("✅ Escrevendo x%0d = %0d", uut.rd, uut.write_back_data);
                end
            end
        end
    end

    always begin
        #5 clock = ~clock;
    end

endmodule

src/simple_hazard.vcd
$date
	Thu Aug 14 22:30:00 2025
$end
$version
	Icarus Verilog
$end
$timescale
	1ps
$end
$scope module testbench_simple $end
$scope module uut $end
$var wire 1 ! MemWrite_safe $end
$var wire 1 " RegWrite_safe $end
$var wire 1 # branch_taken $end
$var wire 1 $ clock $end
$var wire 1 % pc_write $end
$var wire 1 & raw_hazard $end
$var wire 1 ' reset $end
$var wire 1 ( zero $end
$var wire 32 ) write_back_data [31:0] $end
$var wire 5 * rs2 [4:0] $end
$var wire 5 + rs1 [4:0] $end
$var wire 32 , read_data2_fwd [31:0] $end
$var wire 32 - read_data2 [31:0] $end
$var wire 32 . read_data1_fwd [31:0] $end
$var wire 32 / read_data1 [31:0] $end
$var wire 5 0 rd [4:0] $end
$var wire 32 1 pc_prox [31:0] $end
$var wire 32 2 pc_plus4 [31:0] $end
$var wire 32 3 pc [31:0] $end
$var wire 7 4 opcode [6:0] $end
$var wire 32 5 instrucao [31:0] $end
$var wire 32 6 immediate [31:0] $end
$var wire 7 7 funct7 [6:0] $end
$var wire 3 8 funct3 [2:0] $end
$var wire 32 9 branch_alvo [31:0] $end
$var wire 32 : alu_result [31:0] $end
$var wire 32 ; alu_entrada2 [31:0] $end
$var wire 4 < alu_control [3:0] $end
$var wire 1 = RegWrite $end
$var wire 1 > MemtoReg $end
$var wire 1 ? MemWrite $end
$var wire 32 @ MemRead_data [31:0] $end
$var wire 1 A MemRead $end
$var wire 1 B Branch $end
$var wire 1 C ALUSrc $end
$var wire 2 D ALUOp [1:0] $end
$var reg 1 E prev_RegWrite $end
$var reg 5 F prev_rd [4:0] $end
$var reg 1 G stall_cycle $end
$scope module InstMem $end
$var wire 32 H instrucao [31:0] $end
$var wire 32 I endereco [31:0] $end
$var integer 32 J i [31:0] $end
$upscope $end
$scope module alu $end
$var wire 32 K entrada1 [31:0] $end
$var wire 32 L entrada2 [31:0] $end
$var wire 1 ( zero $end
$var wire 4 M alu_control [3:0] $end
$var reg 32 N resultado [31:0] $end
$upscope $end
$scope module aluCtrl $end
$var wire 3 O funct3 [2:0] $end
$var wire 7 P funct7 [6:0] $end
$var wire 2 Q ALUOp [1:0] $end
$var reg 4 R alu_control [3:0] $end
$upscope $end
$scope module ctrl $end
$var wire 7 S opcode [6:0] $end
$var reg 2 T ALUOp [1:0] $end
$var reg 1 C ALUSrc $end
$var reg 1 B Branch $end
$var reg 1 A MemRead $end
$var reg 1 ? MemWrite $end
$var reg 1 > MemtoReg $end
$var reg 1 = RegWrite $end
$upscope $end
$scope module dataMem $end
$var wire 1 U MemRead $end
$var wire 1 ! MemWrite $end
$var wire 1 $ clock $end
$var wire 32 V endereco [31:0] $end
$var wire 3 W funct3 [2:0] $end
$var wire 32 X write_data [31:0] $end
$var wire 32 Y read_data [31:0] $end
$var reg 32 Z read_data_reg [31:0] $end
$scope begin $ivl_for_loop0 $end
$var integer 32 [ i [31:0] $end
$upscope $end
$upscope $end
$scope module immGen $end
$var wire 32 \ instrucao [31:0] $end
$var wire 7 ] opcode [6:0] $end
$var reg 32 ^ imm_out [31:0] $end
$upscope $end
$scope module pc_mux $end
$var wire 32 _ entrada1 [31:0] $end
$var wire 32 ` entrada2 [31:0] $end
$var wire 1 # seletor $end
$var wire 32 a saida [31:0] $end
$upscope $end
$scope module pc_reg $end
$var wire 1 $ clock $end
$var wire 32 b pc_prox [31:0] $end
$var wire 1 % pc_write $end
$var wire 1 ' reset $end
$var reg 32 c pc [31:0] $end
$upscope $end
$scope module registradores $end
$var wire 1 " RegWrite $end
$var wire 1 $ clock $end
$var wire 5 d rd [4:0] $end
$var wire 5 e rs1 [4:0] $end
$var wire 5 f rs2 [4:0] $end
$var wire 32 g write_data [31:0] $end
$var reg 32 h read_data1 [31:0] $end
$var reg 32 i read_data2 [31:0] $end
$var integer 32 j i [31:0] $end
$upscope $end
$scope module write_back_mux $end
$var wire 32 k entrada1 [31:0] $end
$var wire 32 l entrada2 [31:0] $end
$var wire 1 > seletor $end
$var wire 32 m saida [31:0] $end
$upscope $end
$upscope $end
$upscope $end
$enddefinitions $end
#0
$dumpvars
b1111 m
bx l
b1111 k
b100000 j
b0 i
b0 h
b1111 g
b1111 f
b0 e
b10 d
b0 c
b100 b
b100 a
b1111 `
b100 _
b1111 ^
b10011 ]
b111100000000000100010011 \
b100000000 [
bx Z
bx Y
b0 X
b0 W
b1111 V
0U
b0 T
b10011 S
b0 R
b0 Q
b0 P
b0 O
b1111 N
b0 M
b1111 L
b0 K
b1111 J
b0 I
b111100000000000100010011 H
0G
b0 F
0E
b0 D
1C
0B
0A
bx @
0?
0>
1=
b0 <
b1111 ;
b1111 :
b1111 9
b0 8
b0 7
b1111 6
b111100000000000100010011 5
b10011 4
b0 3
b100 2
b100 1
b10 0
b0 /
b0 .
b0 -
b0 ,
b0 +
b1111 *
b1111 )
0(
1'
0&
1%
0$
0#
1"
0!
$end
#5000
b0 @
b0 Y
b0 Z
b0 l
1$
#10000
0$
0'
#15000
0%
1&
b0 )
b0 g
b0 m
b0 ,
1(
b0 :
b0 N
b0 V
b0 k
0!
0"
b0 ;
b0 L
b1111 -
b1111 X
b1111 i
b1000 <
b1000 M
b1000 R
1?
0=
1C
b0 6
b0 ^
b100011 ]
b10 *
b10 f
b1 8
b1 O
b1 W
b0 0
b0 d
b100011 4
b100011 S
b1000000001000000100011 5
b1000000001000000100011 H
b1000000001000000100011 \
b1000 1
b1000 a
b1000 b
b100 9
b100 `
b1000 2
b1000 _
b100 3
b100 I
b100 c
1E
b10 F
1$
#20000
0$
#25000
1!
b1111 ,
1%
0&
1G
0E
1$
#30000
0$
#35000
b1100100 )
b1100100 g
b1100100 m
b0 ,
0(
b1100100 :
b1100100 N
b1100100 V
b1100100 k
1"
0!
b1100100 ;
b1100100 L
b0 -
b0 X
b0 i
b0 <
b0 M
b0 R
1=
1C
0?
b1100100 6
b1100100 ^
b10011 ]
b11 7
b11 P
b100 *
b100 f
b0 8
b0 O
b0 W
b11 0
b11 d
b10011 4
b10011 S
b110010000000000000110010011 5
b110010000000000000110010011 H
b110010000000000000110010011 \
b1100 1
b1100 a
b1100 b
b1101100 9
b1101100 `
b1100 2
b1100 _
b1000 3
b1000 I
b1000 c
0G
b0 F
1$
#40000
0$
#45000
0%
1&
b0 )
b0 g
b0 m
1(
b0 :
b0 N
b0 V
b0 k
0!
0"
b0 ,
b10 ;
b10 L
b1100100 -
b1100100 X
b1100100 i
b1000 <
b1000 M
b1000 R
1?
0=
1C
b10 6
b10 ^
b100011 ]
b0 7
b0 P
b11 *
b11 f
b1 8
b1 O
b1 W
b10 0
b10 d
b100011 4
b100011 S
b1100000001000100100011 5
b1100000001000100100011 H
b1100000001000100100011 \
b10000 1
b10000 a
b10000 b
1E
b11 F
b1110 9
b1110 `
b10000 2
b10000 _
b1100 3
b1100 I
b1100 c
1$
#50000
0$
#55000
1!
b1100100 ,
1%
0&
1G
0E
1$
#60000
0$
#65000
b0 ,
1U
1"
0!
b0 ;
b0 L
b0 -
b0 X
b0 i
1>
1A
1=
1C
0?
b0 6
b0 ^
b11 ]
b0 *
b0 f
b100 0
b100 d
b11 4
b11 S
b1001000000011 5
b1001000000011 H
b1001000000011 \
b10100 1
b10100 a
b10100 b
0G
b10 F
b10000 9
b10000 `
b10100 2
b10100 _
b10000 3
b10000 I
b10000 c
1$
#70000
0$
#75000
b1111 ,
b10 ;
b10 L
b1111 -
b1111 X
b1111 i
b10 6
b10 ^
b10 *
b10 f
b101 0
b101 d
b1000000001001010000011 5
b1000000001001010000011 H
b1000000001001010000011 \
b11000 1
b11000 a
b11000 b
b10110 9
b10110 `
b11000 2
b11000 _
b10100 3
b10100 I
b10100 c
1E
b100 F
b1100100 )
b1100100 g
b1100100 m
b1100100 @
b1100100 Y
b1100100 Z
b1100100 l
1$
#80000
0$
#85000
0"
0%
b11111111111111111111111111110001 .
b11111111111111111111111111110001 K
1&
b0 ,
0(
b11111111111111111111111111110001 :
b11111111111111111111111111110001 N
b11111111111111111111111111110001 V
b11111111111111111111111111110001 k
b11111111111111111111111111110001 )
b11111111111111111111111111110001 g
b11111111111111111111111111110001 m
0U
b0 ;
b0 L
b0 -
b0 X
b0 i
b1100100 /
b1100100 h
b1 <
b1 M
b1 R
b10 D
b10 Q
b10 T
0>
1=
0C
0A
b0 6
b0 ^
b110011 ]
b100000 7
b100000 P
b100 *
b100 f
b101 +
b101 e
b0 8
b0 O
b0 W
b110 0
b110 d
b110011 4
b110011 S
b1000000010000101000001100110011 5
b1000000010000101000001100110011 H
b1000000010000101000001100110011 \
b11100 1
b11100 a
b11100 b
b101 F
b11000 9
b11000 `
b11100 2
b11100 _
b11000 3
b11000 I
b11000 c
1$
#90000
0$
#95000
b1100100 )
b1100100 g
b1100100 m
b1100100 :
b1100100 N
b1100100 V
b1100100 k
1"
b1100100 .
b1100100 K
1%
0&
1G
0E
b0 @
b0 Y
b0 Z
b0 l
1$
#100000
0$
#105000
b11 <
b11 M
b11 R
b0 7
b0 P
b110 8
b110 O
b110 W
b111 0
b111 d
b10000101110001110110011 5
b10000101110001110110011 H
b10000101110001110110011 \
b100000 1
b100000 a
b100000 b
0G
1E
b110 F
b11100 9
b11100 `
b100000 2
b100000 _
b11100 3
b11100 I
b11100 c
1$
#110000
0$
#115000
b100 )
b100 g
b100 m
b100 :
b100 N
b100 V
b100 k
b1111 ;
b1111 L
b10 <
b10 M
b10 R
1C
b0 D
b0 Q
b0 T
1=
b1111 6
b1111 ^
b10011 ]
b1111 *
b1111 f
b110 +
b110 e
b111 8
b111 O
b111 W
b1000 0
b1000 d
b10011 4
b10011 S
b111100110111010000010011 5
b111100110111010000010011 H
b111100110111010000010011 \
b100100 1
b100100 a
b100100 b
b101111 9
b101111 `
b100100 2
b100100 _
b100000 3
b100000 I
b100000 c
b111 F
1$
#120000
0$
#125000
b1100100 )
b1100100 g
b1100100 m
b1100100 :
b1100100 N
b1100100 V
b1100100 k
b0 ;
b0 L
b1001 <
b1001 M
b1001 R
b10 D
b10 Q
b10 T
1=
0C
b0 6
b0 ^
b110011 ]
b100 *
b100 f
b111 +
b111 e
b101 8
b101 O
b101 W
b1001 0
b1001 d
b110011 4
b110011 S
b10000111101010010110011 5
b10000111101010010110011 H
b10000111101010010110011 \
b101000 1
b101000 a
b101000 b
b1000 F
b100100 9
b100100 `
b101000 2
b101000 _
b100100 3
b100100 I
b100100 c
1$
#130000
0$
#135000
0#
b11111111111111111111111110011100 )
b11111111111111111111111110011100 g
b11111111111111111111111110011100 m
b1100100 ;
b1100100 L
0(
b11111111111111111111111110011100 :
b11111111111111111111111110011100 N
b11111111111111111111111110011100 V
b11111111111111111111111110011100 k
b1100100 ,
b0 .
b0 K
0"
b1100100 -
b1100100 X
b1100100 i
b0 /
b0 h
b1 <
b1 M
b1 R
1B
b1 D
b1 Q
b1 T
0=
b1000 6
b1000 ^
b1100011 ]
b101 *
b101 f
b100 +
b100 e
b0 8
b0 O
b0 W
b1000 0
b1000 d
b1100011 4
b1100011 S
b10100100000010001100011 5
b10100100000010001100011 H
b10100100000010001100011 \
b101100 1
b101100 a
b101100 b
b110000 9
b110000 `
b101100 2
b101100 _
b101000 3
b101000 I
b101000 c
b1001 F
1$
#140000
0$
#145000
b1 )
b1 g
b1 m
b1 :
b1 N
b1 V
b1 k
b0 ,
b1 ;
b1 L
1"
b0 <
b0 M
b0 R
b0 -
b0 X
b0 i
1C
1=
b0 D
b0 Q
b0 T
0B
b1 6
b1 ^
b10011 ]
b1 *
b1 f
b0 +
b0 e
b1010 0
b1010 d
b10011 4
b10011 S
b100000000010100010011 5
b100000000010100010011 H
b100000000010100010011 \
b110000 1
b110000 a
b110000 b
0E
b1000 F
b101101 9
b101101 `
b110000 2
b110000 _
b101100 3
b101100 I
b101100 c
1$
#150000
0$
#155000
b0 )
b0 g
b0 m
1(
b0 :
b0 N
b0 V
b0 k
b0 ;
b0 L
b0 6
b0 ^
b0 *
b0 f
b0 0
b0 d
b10011 5
b10011 H
b10011 \
b110100 1
b110100 a
b110100 b
b110000 9
b110000 `
b110100 2
b110100 _
b110000 3
b110000 I
b110000 c
1E
b1010 F
1$
#160000
0$
#165000
bx )
bx g
bx m
x(
bx :
bx N
bx V
bx k
0"
bx ;
bx L
bx .
bx K
bx ,
bx -
bx X
bx i
bx /
bx h
0=
0C
bx ]
bx 7
bx P
bx *
bx f
bx +
bx e
bx 8
bx O
bx W
bx 0
bx d
bx 4
bx S
bx 5
bx H
bx \
b111000 1
b111000 a
b111000 b
b0 F
b110100 9
b110100 `
b111000 2
b111000 _
b110100 3
b110100 I
b110100 c
1$
#170000
0$
#175000
b111100 1
b111100 a
b111100 b
b111000 9
b111000 `
b111100 2
b111100 _
b111000 3
b111000 I
b111000 c
0E
bx F
1$
#180000
0$
#185000
b1000000 1
b1000000 a
b1000000 b
b111100 9
b111100 `
b1000000 2
b1000000 _
b111100 3
b111100 I
b111100 c
1$
#190000
0$
#195000
b1000100 1
b1000100 a
b1000100 b
b1000000 9
b1000000 `
b1000100 2
b1000100 _
b1000000 3
b1000000 I
b1000000 c
1$
#200000
0$
#205000
b1001000 1
b1001000 a
b1001000 b
b1000100 9
b1000100 `
b1001000 2
b1001000 _
b1000100 3
b1000100 I
b1000100 c
1$
#210000
0$
#215000
b1001100 1
b1001100 a
b1001100 b
b1001000 9
b1001000 `
b1001100 2
b1001100 _
b1001000 3
b1001000 I
b1001000 c
1$
#220000
0$
#225000
b1010000 1
b1010000 a
b1010000 b
b1001100 9
b1001100 `
b1010000 2
b1010000 _
b1001100 3
b1001100 I
b1001100 c
1$
#230000
0$
#235000
b1010100 1
b1010100 a
b1010100 b
b1010000 9
b1010000 `
b1010100 2
b1010100 _
b1010000 3
b1010000 I
b1010000 c
1$
#240000
0$
#245000
b1011000 1
b1011000 a
b1011000 b
b1010100 9
b1010100 `
b1011000 2
b1011000 _
b1010100 3
b1010100 I
b1010100 c
1$
#250000
0$
#255000
b1011100 1
b1011100 a
b1011100 b
b1011000 9
b1011000 `
b1011100 2
b1011100 _
b1011000 3
b1011000 I
b1011000 c
1$
#260000
0$
