src/mux2.v
module mux2 #(parameter WIDTH = 32)(
    input wire seletor,
    input wire [WIDTH-1:0] entrada1,
    input wire [WIDTH-1:0] entrada2,
    output wire [WIDTH-1:0] saida
);
    assign saida = (seletor) ? entrada2 : entrada1;

endmodule

src/data_memory.v
module data_memory(
    input wire clock,
    input wire MemRead, MemWrite,
    input wire [31:0] endereco,
    input wire [31:0] write_data,
    output wire [31:0] read_data
);
    reg [31:0] memoria [0:255];

    // Inicializar memória com zeros para debug
    initial begin
        for (integer i = 0; i < 256; i = i + 1) begin
            memoria[i] = 32'h00000000;
        end
    end

    // Leitura (word-aligned, divide por 4)
    assign read_data = MemRead ? memoria[endereco[9:2]] : 32'b0;

    // Escrita
    always @(posedge clock) begin
        if (MemWrite) begin
            memoria[endereco[9:2]] <= write_data;
            // Debug da escrita
            $display("DEBUG: Escrevendo endereco[%0d] = %0d (addr_original=%0d)", 
                    endereco[9:2], write_data, endereco);
        end
    end

endmodule

src/alu.v
module alu(
    input wire [31:0] entrada1,
    input wire [31:0] entrada2,
    input wire [3:0] alu_control,
    output reg [31:0] resultado,
    output wire zero
);

    assign zero = (resultado == 32'b0);
    always @(*) begin
        case (alu_control)
           4'b0010: resultado = entrada1 + entrada2;                // ADD
            4'b0110: resultado = entrada1 - entrada2;                // SUB
            4'b0000: resultado = entrada1 & entrada2;                // AND
            4'b0001: resultado = entrada1 | entrada2;                // OR
            4'b0100: resultado = entrada1 ^ entrada2;                // XOR
            4'b0101: resultado = ~(entrada1 | entrada2);             // NOR
            4'b0111: resultado = ($signed(entrada1) < $signed(entrada2)) ? 32'd1 : 32'd0; // SLT (se quiser)
            4'b1000: resultado = entrada1 << entrada2[4:0];          // SLL
            4'b1001: resultado = entrada1 >> entrada2[4:0];          // SRL
            default: resultado = 32'b0;
        endcase
    end

endmodule

src/alu_control.v
module alu_control(
    input  wire [1:0] ALUOp,      // vem do control unit
    input  wire [2:0] funct3,     // instrução
    input  wire [6:0] funct7,     // instrução (usamos bit[5] para distinguir SRL/SRA e ADD/SUB)
    output reg  [3:0] alu_control // código para a ALU
);

    always @(*) begin
        // default
        alu_control = 4'b0000; // ADD por padrão

        case (ALUOp)
            2'b00: begin
                // ALUOp=00: Para loads, stores, e instruções I-type imediatas
                // NOTA: funct3=010 em loads/stores deve usar ADD, não SLT!
                case (funct3)
                    3'b000: alu_control = 4'b0000; // ADD / ADDI / LW / SW
                    3'b001: alu_control = 4'b1000; // SLLI
                    3'b010: alu_control = 4'b0000; // LW/SW (usa ADD) / SLTI - CORRIGIDO!
                    3'b011: alu_control = 4'b0111; // SLTIU (unsigned)
                    3'b100: alu_control = 4'b0100; // XORI
                    3'b101: begin                   // SRLI / SRAI (depende de funct7[5])
                        if (funct7[5]) alu_control = 4'b1010; // SRAI
                        else           alu_control = 4'b1001; // SRLI
                    end
                    3'b110: alu_control = 4'b0011; // ORI
                    3'b111: alu_control = 4'b0010; // ANDI
                    default: alu_control = 4'b0000;
                endcase
            end

            2'b01: begin
                // Branches — normalmente comparam usando SUB (BEQ/BNE) e outros sinais externos interpretam resultado
                alu_control = 4'b0001; // SUB
            end

            2'b10: begin
                // R-type: usar funct3 e funct7
                case (funct3)
                    3'b000: begin
                        // ADD or SUB (funct7 = 0100000 indica SUB em RV32)
                        if (funct7 == 7'b0100000) alu_control = 4'b0001; // SUB
                        else                      alu_control = 4'b0000; // ADD
                    end
                    3'b001: alu_control = 4'b1000; // SLL
                    3'b010: alu_control = 4'b0110; // SLT (signed)
                    3'b011: alu_control = 4'b0111; // SLTU (unsigned)
                    3'b100: alu_control = 4'b0100; // XOR
                    3'b101: begin
                        // SRL or SRA (funct7[5] == 1 -> SRA)
                        if (funct7[5]) alu_control = 4'b1010; // SRA
                        else           alu_control = 4'b1001; // SRL
                    end
                    3'b110: alu_control = 4'b0011; // OR
                    3'b111: alu_control = 4'b0010; // AND
                    default: alu_control = 4'b0000;
                endcase
            end

            default: begin
                // segurança: ADD por padrão
                alu_control = 4'b0000;
            end
        endcase
    end

endmodule

src/imm_gen.v
module imm_gen (
    input  wire [31:0] instrucao,
    output reg  [31:0] imm_out
);

    wire [6:0] opcode = instrucao[6:0];

    always @(*) begin
        case (opcode)
            // I-type (ex.: addi, lw, jalr)
            7'b0000011, // LW
            7'b0010011, // ADDI
            7'b1100111: // JALR
                imm_out = {{20{instrucao[31]}}, instrucao[31:20]};

            // S-type (ex.: sw)
            7'b0100011:
                imm_out = {{20{instrucao[31]}}, instrucao[31:25], instrucao[11:7]};

            // B-type (ex.: beq, bne) - CORRIGIDO
            7'b1100011:
                imm_out = {{19{instrucao[31]}}, instrucao[31], instrucao[7],
                           instrucao[30:25], instrucao[11:8], 1'b0};

            // U-type (ex.: lui, auipc)
            7'b0110111, // LUI
            7'b0010111: // AUIPC
                imm_out = {instrucao[31:12], 12'b0};

            // J-type (ex.: jal)
            7'b1101111:
                imm_out = {{11{instrucao[31]}}, instrucao[31],
                           instrucao[19:12], instrucao[20],
                           instrucao[30:21], 1'b0};

            // Default (R-type ou instrução inválida)
            default:
                imm_out = 32'b0;
        endcase
    end

endmodule

src/register.v
module register(
    input logic clock,
    input logic RegWrite,
    input logic [4:0] rs1, rs2, rd,
    input logic [31:0] write_data,
    output logic [31:0] read_data1, read_data2
);
    reg [31:0] registradores [0:31];

    integer i;
    initial begin
        for (i = 0; i < 32; i = i + 1)
            registradores[i] = 32'b0;
    end

    assign read_data1 = (rs1 == 5'd0) ? 32'b0 : registradores[rs1];
    assign read_data2 = (rs2 == 5'd0) ? 32'b0 : registradores[rs2];

    always_ff @(posedge clock) begin
        if (RegWrite && rd != 5'd0) begin
            registradores[rd] <= write_data;
        end
    end

endmodule

src/control.v
module control(
    input wire [6:0] opcode,
    output reg Branch, MemRead, MemWrite, ALUSrc, RegWrite,
    output reg MemtoReg,
    output reg [1:0] ALUOp    
);

    always @(*) begin
        // Inicializar todos os sinais com 0
        Branch = 1'b0;
        MemRead = 1'b0;
        MemWrite = 1'b0;
        ALUSrc = 1'b0;
        RegWrite = 1'b0;
        MemtoReg = 1'b0;
        ALUOp = 2'b00;
        
        case(opcode)
            7'b0110011: begin // R-type
                RegWrite = 1'b1;
                ALUOp = 2'b10;  // R-type precisa usar funct3/funct7
                ALUSrc = 1'b0;  // usa rs2
            end
            
            7'b0100011: begin // S-type (SW, SH, SB)
                MemWrite = 1'b1;
                ALUSrc = 1'b1;  // usa immediate
                ALUOp = 2'b00;  // FORÇA ADD para calcular endereço
            end
            
            7'b1100011: begin // B-type (BEQ, BNE, etc)
                Branch = 1'b1;
                ALUOp = 2'b01;  // branch usa SUB
                ALUSrc = 1'b0;  // compara rs1 com rs2
            end
            
            7'b0110111: begin // U-type - LUI
                RegWrite = 1'b1;
                ALUSrc = 1'b0;
                ALUOp = 2'b00;
            end
            
            7'b1101111: begin // J-type - JAL
                RegWrite = 1'b1;
                Branch = 1'b1;
                MemtoReg = 1'b0;
                ALUOp = 2'b00;
            end
            
            7'b0000011: begin // I-type - load (LW, LH, LB)
                RegWrite = 1'b1;
                MemRead = 1'b1;
                MemtoReg = 1'b1;  // write back vem da memória
                ALUSrc = 1'b1;    // usa immediate
                ALUOp = 2'b00;    // FORÇA ADD para calcular endereço
            end
            
            7'b0010011: begin // I-type - immediate arithmetic (ADDI, SLTI, etc)
                RegWrite = 1'b1;
                ALUSrc = 1'b1;    // usa immediate
                ALUOp = 2'b00;    // usa funct3 para determinar operação
            end
            
            default: begin
                // Todos os sinais já estão em 0
            end
        endcase
    end

endmodule

src/instruction_memory.v
module instruction_memory(
    input wire [31:0]endereco,
    output wire [31:0] instrucao
);
    reg [31:0] memoria [0:8];

    initial begin
        $readmemb("programa.bin", memoria);
    end

    assign instrucao = memoria[endereco[9:2]];
endmodule

src/pc.v
module pc(
    input wire clock,
    input wire reset,
    input wire [31:0] pc_prox,
    output reg [31:0] pc
);

    always @(posedge clock or posedge reset) begin
        if (reset)
            pc <= 0;
        else
            pc <= pc_prox;
    end

endmodule

src/cpu.v
module cpu (
    input wire clock,
    input wire reset
);

    // PC e Instrução
    wire [31:0] pc, pc_prox, pc_plus4;
    wire [31:0] instrucao;

    assign pc_plus4 = pc + 32'd4;

    pc pc_reg(
        .clock(clock),
        .reset(reset),
        .pc_prox(pc_prox),
        .pc(pc)
    );

    instruction_memory InstMem (
        .endereco(pc),
        .instrucao(instrucao)
    );

    // Decodificação
    wire [6:0] opcode = instrucao[6:0];
    wire [4:0] rd     = instrucao[11:7];
    wire [2:0] funct3 = instrucao[14:12];
    wire [4:0] rs1    = instrucao[19:15];
    wire [4:0] rs2    = instrucao[24:20];
    wire [6:0] funct7 = instrucao[31:25];

    wire [31:0] read_data1, read_data2;
    wire [31:0] immediate;

    wire Branch, MemRead, MemWrite, ALUSrc, RegWrite;
    wire MemtoReg;
    wire [1:0] ALUOp; 

    control ctrl(
        .opcode(opcode),
        .Branch(Branch),
        .MemRead(MemRead),
        .MemtoReg(MemtoReg),
        .MemWrite(MemWrite),
        .ALUSrc(ALUSrc),
        .RegWrite(RegWrite),
        .ALUOp(ALUOp)
    );

    register registradores(
        .clock(clock),
        .RegWrite(RegWrite),
        .rs1(rs1),
        .rs2(rs2),
        .rd(rd),
        .write_data(write_back_data),
        .read_data1(read_data1),
        .read_data2(read_data2)
    );

    imm_gen immGen(
        .instrucao(instrucao),
        .imm_out(immediate)
    );

    // ALU
    wire [3:0] alu_control;
    wire [31:0] alu_entrada2 = ALUSrc ? immediate : read_data2;
    wire [31:0] alu_result;
    wire zero;

    alu_control aluCtrl(
        .ALUOp(ALUOp),
        .funct3(funct3),
        .funct7(funct7),
        .alu_control(alu_control)
    );

    alu alu(
        .entrada1(read_data1),
        .entrada2(alu_entrada2),
        .alu_control(alu_control),
        .resultado(alu_result),
        .zero(zero)
    );

    // Memória de Dados
    wire [31:0] MemRead_data;

    data_memory dataMem(
        .clock(clock),
        .MemRead(MemRead),
        .MemWrite(MemWrite),
        .endereco(alu_result),
        .write_data(read_data2),
        .read_data(MemRead_data)
    );

    // Write Back
    wire [31:0] write_back_data;

    mux2 #(.WIDTH(32)) write_back_mux(
        .seletor(MemtoReg),
        .entrada1(alu_result),
        .entrada2(MemRead_data),
        .saida(write_back_data)
    );

    // Controle de Desvio (Branch)
    wire [31:0] branch_alvo = pc + immediate;
    wire branch_taken = Branch & zero;

    mux2 #(.WIDTH(32)) pc_mux(
        .seletor(branch_taken),
        .entrada1(pc_plus4),
        .entrada2(branch_alvo),
        .saida(pc_prox)
    );

endmodule

src/testbench.v
`timescale 1ns/1ps

module debug_detalhado;

    reg clock;
    reg reset;
    integer cycle_count;

    cpu uut (
        .clock(clock),
        .reset(reset)
    );

    initial begin
        $dumpfile("testbench.vcd");
        $dumpvars(0, uut);

        clock = 0;
        reset = 1;
        cycle_count = 0;

        #10;
        reset = 0;

        // Aguardar execução
        #100;

        $display("\n=== ANÁLISE DETALHADA CORRIGIDA ===");
        
        // Decodificação manual das instruções
        $display("\n--- DECODIFICAÇÃO CORRETA ---");
        decode_instructions();
        
        // Estado final
        show_detailed_state();
        
        // Validação do Teste 1
        validate_arithmetic_test();

        $finish;
    end

    // Decodificação correta das instruções
    task decode_instructions;
        reg [31:0] instr;
        reg [6:0] opcode;
        reg [4:0] rd, rs1, rs2;
        reg [2:0] funct3;
        reg [6:0] funct7;
        reg signed [11:0] imm_i;
        begin
            // Instrução 0
            instr = uut.InstMem.memoria[0]; // 00a00093
            opcode = instr[6:0];
            rd = instr[11:7];
            rs1 = instr[19:15];
            imm_i = instr[31:20];
            $display("Instr[0]: %h → ADDI x%0d, x%0d, %0d", instr, rd, rs1, imm_i);
            
            // Instrução 1  
            instr = uut.InstMem.memoria[1]; // 00300213
            rd = instr[11:7];
            rs1 = instr[19:15];
            imm_i = instr[31:20];
            $display("Instr[1]: %h → ADDI x%0d, x%0d, %0d", instr, rd, rs1, imm_i);
            
            // Instrução 2 (R-type)
            instr = uut.InstMem.memoria[2]; // 002081b3
            opcode = instr[6:0];
            rd = instr[11:7];
            rs1 = instr[19:15];
            rs2 = instr[24:20];
            funct3 = instr[14:12];
            funct7 = instr[31:25];
            $display("Instr[2]: %h → ADD x%0d, x%0d, x%0d (funct3=%b, funct7=%b)", 
                    instr, rd, rs1, rs2, funct3, funct7);
            
            // Instrução 3 (R-type)  
            instr = uut.InstMem.memoria[3]; // 40208233
            rd = instr[11:7];
            rs1 = instr[19:15];
            rs2 = instr[24:20];
            funct3 = instr[14:12];
            funct7 = instr[31:25];
            $display("Instr[3]: %h → SUB x%0d, x%0d, x%0d (funct3=%b, funct7=%b)", 
                    instr, rd, rs1, rs2, funct3, funct7);
            
            // Instrução 4
            instr = uut.InstMem.memoria[4]; // ffb08293
            rd = instr[11:7];
            rs1 = instr[19:15];
            imm_i = instr[31:20];
            $display("Instr[4]: %h → ADDI x%0d, x%0d, %0d", instr, rd, rs1, imm_i);
        end
    endtask

    // Estado detalhado
    task show_detailed_state;
        begin
            $display("\n--- REGISTRADORES DETALHADOS ---");
            $display("x0 = %0d (sempre zero)", uut.registradores.registradores[0]);
            $display("x1 = %0d (deveria ser 10)", uut.registradores.registradores[1]);
            $display("x2 = %0d (deveria ser 3)", uut.registradores.registradores[2]);
            $display("x3 = %0d (deveria ser 13)", uut.registradores.registradores[3]);
            $display("x4 = %0d (deveria ser 7)", uut.registradores.registradores[4]);
            $display("x5 = %0d (deveria ser 5)", uut.registradores.registradores[5]);
            
            $display("\n--- ANÁLISE DOS PROBLEMAS ---");
            if (uut.registradores.registradores[2] != 3) begin
                $display("❌ PROBLEMA: x2 = %0d, mas deveria ser 3", uut.registradores.registradores[2]);
                $display("   → Verifique se ADDI x2, x0, 3 está escrevendo em x2 corretamente");
            end
            
            if (uut.registradores.registradores[3] != 13) begin
                $display("❌ PROBLEMA: x3 = %0d, mas deveria ser 13", uut.registradores.registradores[3]);
                $display("   → ADD x3, x1, x2 não está funcionando corretamente");
                $display("   → read_data1 deveria ser 10, read_data2 deveria ser 3");
            end
            
            if (uut.registradores.registradores[4] != 7) begin
                $display("❌ PROBLEMA: x4 = %0d, mas deveria ser 7", uut.registradores.registradores[4]);
                $display("   → SUB x4, x1, x2 não está funcionando corretamente");
            end
        end
    endtask

    // Validação específica
    task validate_arithmetic_test;
        integer errors;
        begin
            errors = 0;
            $display("\n--- VALIDAÇÃO TESTE ARITMÉTICA ---");
            
            if (uut.registradores.registradores[1] == 10) 
                $display("✓ x1 = 10 (ADDI correto)");
            else begin
                $display("✗ x1 = %0d (esperado: 10)", uut.registradores.registradores[1]);
                errors = errors + 1;
            end
            
            if (uut.registradores.registradores[2] == 3) 
                $display("✓ x2 = 3 (ADDI correto)");
            else begin
                $display("✗ x2 = %0d (esperado: 3)", uut.registradores.registradores[2]);
                errors = errors + 1;
            end
            
            if (uut.registradores.registradores[3] == 13) 
                $display("✓ x3 = 13 (ADD correto)");
            else begin
                $display("✗ x3 = %0d (esperado: 13)", uut.registradores.registradores[3]);
                errors = errors + 1;
            end
            
            if (uut.registradores.registradores[4] == 7) 
                $display("✓ x4 = 7 (SUB correto)");
            else begin
                $display("✗ x4 = %0d (esperado: 7)", uut.registradores.registradores[4]);
                errors = errors + 1;
            end
            
            if (uut.registradores.registradores[5] == 5) 
                $display("✓ x5 = 5 (ADDI negativo correto)");
            else begin
                $display("✗ x5 = %0d (esperado: 5)", uut.registradores.registradores[5]);
                errors = errors + 1;
            end
            
            $display("\nRESULTADO: %0d/5 testes passaram", 5-errors);
            
            if (errors == 0)
                $display("🎉 TODOS OS TESTES PASSARAM!");
            else
                $display("❌ %0d TESTES FALHARAM", errors);
        end
    endtask

    // Monitor ciclo por ciclo com mais detalhes
    always @(posedge clock) begin
        if (!reset) begin
            cycle_count = cycle_count + 1;
            $display("\n=== Ciclo %0d ===", cycle_count);
            $display("PC=%0d Instrucao=%h", uut.pc, uut.instrucao);
            
            // Mostrar campos da instrução
            $display("rd=%0d rs1=%0d rs2=%0d funct3=%b", 
                    uut.rd, uut.rs1, uut.rs2, uut.funct3);
            
            // Mostrar dados dos registradores ANTES da operação
            $display("read_data1=%0d (x%0d) read_data2=%0d (x%0d)", 
                    uut.read_data1, uut.rs1, uut.read_data2, uut.rs2);
            
            // Mostrar operação ALU
            $display("ALU: %0d %s %0d = %0d", 
                    uut.read_data1, 
                    (uut.alu_control == 4'b0000) ? "ADD" :
                    (uut.alu_control == 4'b0001) ? "SUB" : "OP", 
                    (uut.ALUSrc) ? uut.immediate : uut.read_data2, 
                    uut.alu_result);
            
            // Mostrar se vai escrever no registrador
            if (uut.RegWrite) begin
                $display("→ Escrevendo x%0d = %0d", uut.rd, uut.write_back_data);
            end
        end
    end

    always begin
        #5 clock = ~clock;
    end

endmodule

src/testbench.vcd
$date
	Fri Aug 08 21:31:19 2025
$end
$version
	Icarus Verilog
$end
$timescale
	1ps
$end
$scope module debug_detalhado $end
$scope module uut $end
$var wire 1 ! branch_taken $end
$var wire 1 " clock $end
$var wire 1 # reset $end
$var wire 1 $ zero $end
$var wire 32 % write_back_data [31:0] $end
$var wire 5 & rs2 [4:0] $end
$var wire 5 ' rs1 [4:0] $end
$var wire 32 ( read_data2 [31:0] $end
$var wire 32 ) read_data1 [31:0] $end
$var wire 5 * rd [4:0] $end
$var wire 32 + pc_prox [31:0] $end
$var wire 32 , pc_plus4 [31:0] $end
$var wire 32 - pc [31:0] $end
$var wire 7 . opcode [6:0] $end
$var wire 32 / instrucao [31:0] $end
$var wire 32 0 immediate [31:0] $end
$var wire 7 1 funct7 [6:0] $end
$var wire 3 2 funct3 [2:0] $end
$var wire 32 3 branch_alvo [31:0] $end
$var wire 32 4 alu_result [31:0] $end
$var wire 32 5 alu_entrada2 [31:0] $end
$var wire 4 6 alu_control [3:0] $end
$var wire 1 7 RegWrite $end
$var wire 1 8 MemtoReg $end
$var wire 1 9 MemWrite $end
$var wire 32 : MemRead_data [31:0] $end
$var wire 1 ; MemRead $end
$var wire 1 < Branch $end
$var wire 1 = ALUSrc $end
$var wire 2 > ALUOp [1:0] $end
$scope module InstMem $end
$var wire 32 ? instrucao [31:0] $end
$var wire 32 @ endereco [31:0] $end
$upscope $end
$scope module alu $end
$var wire 32 A entrada2 [31:0] $end
$var wire 1 $ zero $end
$var wire 32 B entrada1 [31:0] $end
$var wire 4 C alu_control [3:0] $end
$var reg 32 D resultado [31:0] $end
$upscope $end
$scope module aluCtrl $end
$var wire 3 E funct3 [2:0] $end
$var wire 7 F funct7 [6:0] $end
$var wire 2 G ALUOp [1:0] $end
$var reg 4 H alu_control [3:0] $end
$upscope $end
$scope module ctrl $end
$var wire 7 I opcode [6:0] $end
$var reg 2 J ALUOp [1:0] $end
$var reg 1 = ALUSrc $end
$var reg 1 < Branch $end
$var reg 1 ; MemRead $end
$var reg 1 9 MemWrite $end
$var reg 1 8 MemtoReg $end
$var reg 1 7 RegWrite $end
$upscope $end
$scope module dataMem $end
$var wire 1 ; MemRead $end
$var wire 1 9 MemWrite $end
$var wire 1 " clock $end
$var wire 32 K endereco [31:0] $end
$var wire 32 L write_data [31:0] $end
$var wire 32 M read_data [31:0] $end
$scope begin $ivl_for_loop0 $end
$var integer 32 N i [31:0] $end
$upscope $end
$upscope $end
$scope module immGen $end
$var wire 32 O instrucao [31:0] $end
$var wire 7 P opcode [6:0] $end
$var reg 32 Q imm_out [31:0] $end
$upscope $end
$scope module pc_mux $end
$var wire 32 R entrada1 [31:0] $end
$var wire 32 S entrada2 [31:0] $end
$var wire 1 ! seletor $end
$var wire 32 T saida [31:0] $end
$upscope $end
$scope module pc_reg $end
$var wire 1 " clock $end
$var wire 32 U pc_prox [31:0] $end
$var wire 1 # reset $end
$var reg 32 V pc [31:0] $end
$upscope $end
$scope module registradores $end
$var wire 1 7 RegWrite $end
$var wire 1 " clock $end
$var wire 5 W rd [4:0] $end
$var wire 5 X rs1 [4:0] $end
$var wire 5 Y rs2 [4:0] $end
$var wire 32 Z write_data [31:0] $end
$var reg 32 [ read_data1 [31:0] $end
$var reg 32 \ read_data2 [31:0] $end
$var integer 32 ] i [31:0] $end
$upscope $end
$scope module write_back_mux $end
$var wire 32 ^ entrada1 [31:0] $end
$var wire 32 _ entrada2 [31:0] $end
$var wire 1 8 seletor $end
$var wire 32 ` saida [31:0] $end
$upscope $end
$upscope $end
$upscope $end
$enddefinitions $end
#0
$dumpvars
b1010 `
b0 _
b1010 ^
b100000 ]
b0 \
b0 [
b1010 Z
b1010 Y
b0 X
b1 W
b0 V
b100 U
b100 T
b1010 S
b100 R
b1010 Q
b10011 P
b101000000000000010010011 O
b100000000 N
b0 M
b0 L
b1010 K
b0 J
b10011 I
b0 H
b0 G
b0 F
b0 E
b1010 D
b0 C
b0 B
b1010 A
b0 @
b101000000000000010010011 ?
b0 >
1=
0<
0;
b0 :
09
08
17
b0 6
b1010 5
b1010 4
b1010 3
b0 2
b0 1
b1010 0
b101000000000000010010011 /
b10011 .
b0 -
b100 ,
b100 +
b1 *
b0 )
b0 (
b0 '
b1010 &
b1010 %
0$
1#
0"
0!
$end
#5000
1"
#10000
0"
0#
#15000
b11 %
b11 Z
b11 `
b11 4
b11 D
b11 K
b11 ^
b11 5
b11 A
b11 0
b11 Q
b11 &
b11 Y
b100 *
b100 W
b1100000000001000010011 /
b1100000000001000010011 ?
b1100000000001000010011 O
b1000 +
b1000 T
b1000 U
b111 3
b111 S
b1000 ,
b1000 R
b100 -
b100 @
b100 V
1"
#20000
0"
#25000
b1010 %
b1010 Z
b1010 `
b1010 4
b1010 D
b1010 K
b1010 ^
b0 5
b0 A
b1010 )
b1010 B
b1010 [
b10 >
b10 G
b10 J
17
0=
b0 0
b0 Q
b110011 P
b10 &
b10 Y
b1 '
b1 X
b11 *
b11 W
b110011 .
b110011 I
b1000001000000110110011 /
b1000001000000110110011 ?
b1000001000000110110011 O
b1100 +
b1100 T
b1100 U
b1000 3
b1000 S
b1100 ,
b1100 R
b1000 -
b1000 @
b1000 V
1"
#30000
0"
#35000
b1 6
b1 C
b1 H
b100000 1
b100000 F
b100 *
b100 W
b1000000001000001000001000110011 /
b1000000001000001000001000110011 ?
b1000000001000001000001000110011 O
b10000 +
b10000 T
b10000 U
b1100 3
b1100 S
b10000 ,
b10000 R
b1100 -
b1100 @
b1100 V
1"
#40000
0"
#45000
b101 %
b101 Z
b101 `
b101 4
b101 D
b101 K
b101 ^
b11111111111111111111111111111011 5
b11111111111111111111111111111011 A
b0 6
b0 C
b0 H
1=
b0 >
b0 G
b0 J
17
b11111111111111111111111111111011 0
b11111111111111111111111111111011 Q
b10011 P
b1111111 1
b1111111 F
b11011 &
b11011 Y
b101 *
b101 W
b10011 .
b10011 I
b11111111101100001000001010010011 /
b11111111101100001000001010010011 ?
b11111111101100001000001010010011 O
b10100 +
b10100 T
b10100 U
b1011 3
b1011 S
b10100 ,
b10100 R
b10000 -
b10000 @
b10000 V
1"
#50000
0"
#55000
bx %
bx Z
bx `
x$
bx 4
bx D
bx K
bx ^
bx 5
bx A
bx (
bx L
bx \
bx )
bx B
bx [
07
0=
b0 0
b0 Q
bx P
bx 1
bx F
bx &
bx Y
bx '
bx X
bx 2
bx E
bx *
bx W
bx .
bx I
bx /
bx ?
bx O
b11000 +
b11000 T
b11000 U
b10100 3
b10100 S
b11000 ,
b11000 R
b10100 -
b10100 @
b10100 V
1"
#60000
0"
#65000
b11100 +
b11100 T
b11100 U
b11000 3
b11000 S
b11100 ,
b11100 R
b11000 -
b11000 @
b11000 V
1"
#70000
0"
#75000
b100000 +
b100000 T
b100000 U
b11100 3
b11100 S
b100000 ,
b100000 R
b11100 -
b11100 @
b11100 V
1"
#80000
0"
#85000
b100100 +
b100100 T
b100100 U
b100000 3
b100000 S
b100100 ,
b100100 R
b100000 -
b100000 @
b100000 V
1"
#90000
0"
#95000
b101000 +
b101000 T
b101000 U
b100100 3
b100100 S
b101000 ,
b101000 R
b100100 -
b100100 @
b100100 V
1"
#100000
0"
#105000
b101100 +
b101100 T
b101100 U
b101000 3
b101000 S
b101100 ,
b101100 R
b101000 -
b101000 @
b101000 V
1"
