src/data_memory.v
module data_memory(
    input logic clock,
    input logic MemRead, MemWrite,
    input logic [31:0] endereco,
    input logic [31:0] write_data,
    output logic [31:0] read_data
);
    logic [31:0] memory [0:255];

    assign read_data = (MemRead) ? memory[endereco[9:2]] : 0; // Read data from the specified endereco

    always_ff @(posedge clock) begin
        if (MemWrite) begin
            memory[endereco[9:2]] <= write_data; // Write data to the specified endereco
        end
    end

endmodule

src/alu.v
module alu(
    input wire [31:0] entrada1,
    input wire [31:0] entrada2,
    input wire [3:0] alu_control,
    output reg [31:0] resultado,
    output wire zero
);

    assign zero = (resultado == 32'b0);
    always @(*) begin
        case (alu_control)
           4'b0010: resultado = entrada1 + entrada2;                // ADD
            4'b0110: resultado = entrada1 - entrada2;                // SUB
            4'b0000: resultado = entrada1 & entrada2;                // AND
            4'b0001: resultado = entrada1 | entrada2;                // OR
            4'b0100: resultado = entrada1 ^ entrada2;                // XOR
            4'b0101: resultado = ~(entrada1 | entrada2);             // NOR
            4'b0111: resultado = ($signed(entrada1) < $signed(entrada2)) ? 32'd1 : 32'd0; // SLT (se quiser)
            4'b1000: resultado = entrada1 << entrada2[4:0];          // SLL
            4'b1001: resultado = entrada1 >> entrada2[4:0];          // SRL
            default: resultado = 32'b0;
        endcase
    end

endmodule

src/alu_control.v
module alu_control(
    input wire [1:0] aluOp,
    input wire [2:0] funct3,
    input wire [6:0] funct7,
    output reg [3:0] alu_control
);

    wire funct7_5 = funct7[5];
    
    always @(*) begin
        case (aluOp)
            2'b00: alu_control = 4'b0010; // Load/Store
            2'b01: alu_control = 4'b0110; // Branch
            2'b10: begin // R-type
                case ({funct7, funct3})
                    4'b0000: alu_control = 4'b0010; // ADD
                    4'b1000: alu_control = 4'b0110; // SUB
                    4'b0001: alu_control = 4'b0000; // SLL
                    4'b0010: alu_control = 4'b0001; // SLT
                    4'b0100: alu_control = 4'b0001; // XOR
                    4'b0110: alu_control = 4'b0000; // OR
                    default: alu_control = 4'b1111; // Invalid operation
                endcase
            end
            default: alu_control = 4'b1111; // Invalid operation
        endcase
    end
endmodule

src/control.v
module control(
    input wire [6:0] opcode,
    output reg Branch, MemRead, MemWrite, ALUSrc, RegWrite,
    output reg MemtoReg[1:0],
    output logic [1:0] ALUOp    
);

    always @(*) begin
        Branch = 1'b0;
        MemRead = 1'b0;
        MemWrite = 1'b0;
        ALUSrc = 1'b0;
        RegWrite = 1'b0;
        MemtoReg = 2'b00;
        ALUOp = 2'b00;
        
        case(opcode)
            7'b0110011: begin // R-type
                RegWrite = 1'b1;
                ALUOp = 2'b10;
                ALUSrc = 1'b0;
            end
            7'b0100011: begin // S-type
                MemWrite = 1'b1;
                ALUSrc = 1'b1;
                ALUOp = 2'b00;
            end
            7'b1100011: begin // B-type
                Branch = 1'b1;
                ALUOp = 2'b01;
                ALUSrc = 1'b0;
            end
            7'b0110111: begin // U-type - LUI
                RegWrite = 1'b1;
                ALUSrc = 1'b0;
            end
            7'b1101111: begin // J-type - JAL
                RegWrite = 1'b1;
                Branch = 1'b1;
                MemtoReg = 1'b0;
            end
            7'b0000011: begin // I-type - load
                RegWrite = 1'b1;
                MemRead = 1'b1;
                MemtoReg = 2'b01;
                ALUSrc = 1'b1;
                ALUOp = 2'b00;
            end
            7'b0010011: begin // I-type - immediate arithmetic
                RegWrite = 1'b1;
                ALUSrc = 1'b1;
                ALUOp = 2'b00;
            end
            default: begin
            end
        endcase
    end

endmodule

src/imm_gen.v
module imm_gen(
    input wire [31:0] instrucao,
    output reg [31:0] immediate
);

wire [6:0] opcode = instrucao[6:0];
wire [2:0] funct3 = instrucao[14:12];

always @(*) begin
        case (opcode)
            7'b0000011, // LW
            7'b0010011: // I-type
                immediate = {{20{instrucao[31]}}, instrucao[31:20]};
            7'b0100011: // SW
                immediate = {{20{instrucao[31]}}, instrucao[31:25], instrucao[11:7]};

            7'b1100011: // BEQ
                immediate = {{19{instrucao[31]}}, instrucao[31], instrucao[7],
                             instrucao[30:25], instrucao[11:8], 1'b0};

            default:
                immediate = 0;
        endcase
    end

endmodule

src/register.v
module register(
    input logic clock,
    input logic RegWrite,
    input logic [4:0] rs1, rs2, rd,
    input logic [31:0] write_data,
    output logic [31:0] read_data1, read_data2
);
    reg [31:0] registradores [0:31];

    integer i;
    initial begin
        for (i = 0; i < 32; i = i + 1)
            registradores[i] = 32'b0;
    end

    assign read_data1 = (rs1 == 5'd0) ? 32'b0 : registradores[rs1];
    assign read_data2 = (rs2 == 5'd0) ? 32'b0 : registradores[rs2];

    always_ff @(posedge clock) begin
        if (RegWrite && rd != 5'd0) begin
            registradores[rd] <= write_data;
        end
    end

endmodule

src/instruction_memory.v
module instruction_memory(
    input wire [31:0]endereco,
    output wire [31:0] instrucao
);
    reg [31:0] memoria [0:9];

    initial $readmemb("programa.bin", memoria);

    assign instrucao = memoria[endereco[9:2]];
endmodule

src/pc.v
module pc(
    input wire clock,
    input wire reset,
    input wire [31:0] pc_prox,
    output reg [31:0] pc
);

    always @(posedge clock or posedge reset) begin
        if (reset)
            pc <= 0;
        else
            pc <= pc_prox;
    end

endmodule

src/mux2.v
module mux2 #(parameter WIDTH = 32)(
    input wire seletor,
    input wire [WIDTH-1:0] entrada1,
    input wire [WIDTH-1:0] entrada2,
    output wire [WIDTH-1:0] saida
);
    assign saida = (seletor) ? entrada2 : entrada1;

endmodule

src/cpu.v
module cpu (
    input wire clock,
    input wire reset
);

    wire [31:0] pc, pc_prox, pc_plus4, branch_alvo;
    wire [31:0] instrucao;

    wire [6:0] opcode = instrucao[6:0];
    wire [2:0] funct3 = instrucao[14:12];
    wire [4:0] rd = instrucao[11:7];
    wire [4:0] rs1 = instrucao[19:15];
    wire [4:0] rs2 = instrucao[24:20];
    wire [6:0] funct7 = instrucao[31:25];

    wire Branch, MemRead, MemtoReg, MemWrite, ALUSrc, RegWrite;
    wire [1:0] ALUOp;
    wire [3:0] alu_control;


    wire [31:0] read_data1, read_data2;
    wire [31:0] immediate;
    wire [31:0] ALUSrc2;
    wire [31:0] alu_result;
    wire zero;

    wire [31:0] mem_read_data, write_back_data;
    wire branch_taken;

    assign pc_plus4 = pc + 4;

    assign branch_alvo = pc + immediate;
    
    assign branch_taken = Branch & zero;

    mux2 #(.WIDTH(32)) ALUSrc_mux(
        .seletor(branch_taken),
        .entrada1(pc_plus4),
        .entrada2(branch_alvo),
        .saida(pc_prox)
    );

    mux2 #(.WIDTH(32)) write_back_mux(
        .seletor(MemtoReg),
        .entrada1(alu_result),
        .entrada2(mem_read_data),
        .saida(write_back_data)
    );

    pc pc_reg(
        .clock(clock),
        .reset(reset),
        .pc_prox(pc_prox),
        .pc(pc)
    );

    instruction_memory InstMem (
        .endereco(pc),
        .instrucao(instrucao)
    );

    register registradores(
        .clock(clock),
        .RegWrite(RegWrite),
        .rs1(rs1),
        .rs2(rs2),
        .rd(rd),
        .write_data(write_back_data),
        .read_data1(read_data1),
        .read_data2(read_data2)
    );

    imm_gen immGen(
        .instrucao(instrucao),
        .immediate(immediate)
    );

    control ctrl(
        .opcode(opcode),
        .Branch(Branch),
        .MemRead(MemRead),
        .MemtoReg(MemtoReg),
        .MemWrite(MemWrite),
        .ALUSrc(ALUSrc),
        .RegWrite(RegWrite),
        .ALUOp(ALUOp)
    );

    alu_control aluCtrl(
        .aluOp(ALUOp),
        .funct3(funct3),
        .funct7(funct7),
        .alu_control(alu_control)
    );

    assign ALUSrc2 = (ALUSrc) ? immediate : read_data2;

    alu alu(
        .entrada1(read_data1),
        .entrada2(ALUSrc2),
        .alu_control(alu_control),
        .resultado(alu_result),
        .zero(zero)
    );


    data_memory dataMem(
        .clock(clock),
        .MemRead(MemRead),
        .MemWrite(MemWrite),
        .endereco(alu_result),
        .write_data(read_data2),
        .read_data(mem_read_data)
    );

    
    
endmodule

src/testbench.v
`timescale 1ns/1ps

module testbench;

    reg clock;
    reg reset;

    cpu uut (
        .clock(clock),
        .reset(reset)
    );

    integer errors;

    initial begin
        $dumpfile("testbench.vcd");
        $dumpvars(0, uut);

        
        clock = 0;
        reset = 1;
        errors = 0;

        #10;
        reset = 0;

        #100;

        $display("=== Resultado do Testbench: ===");

        

        $display("x1 = %d (deve ser 0)", uut.registradores.registradores[1]);
        $display("x4 = %d (deve ser 20)", uut.registradores.registradores[4]);
        $display("x5 = %d (deve ser 16)", uut.registradores.registradores[5]);
        $display("x6 = %d (deve ser 20)", uut.registradores.registradores[6]);
        $display("x7 = %d (deve ser 8)", uut.registradores.registradores[7]);
        $display("Data Memory[1] =%d (deve ser 20)", uut.dataMem.memoria[1]);

        $finish;
    end

   always begin
        #5 clock = ~clock; // Toggle clock every 5 time units
    end
endmodule

src/testbench.vcd
$date
	Mon Aug 04 19:20:22 2025
$end
$version
	Icarus Verilog
$end
$timescale
	1ps
$end
$scope module testbench $end
$scope module uut $end
$var wire 1 ! branch_taken $end
$var wire 1 " clock $end
$var wire 1 # reset $end
$var wire 1 $ zero $end
$var wire 32 % write_back_data [31:0] $end
$var wire 5 & rs2 [4:0] $end
$var wire 5 ' rs1 [4:0] $end
$var wire 32 ( read_data2 [31:0] $end
$var wire 32 ) read_data1 [31:0] $end
$var wire 5 * rd [4:0] $end
$var wire 32 + pc_prox [31:0] $end
$var wire 32 , pc_plus4 [31:0] $end
$var wire 32 - pc [31:0] $end
$var wire 7 . opcode [6:0] $end
$var wire 32 / mem_read_data [31:0] $end
$var wire 32 0 instrucao [31:0] $end
$var wire 32 1 immediate [31:0] $end
$var wire 7 2 funct7 [6:0] $end
$var wire 3 3 funct3 [2:0] $end
$var wire 32 4 branch_alvo [31:0] $end
$var wire 32 5 alu_result [31:0] $end
$var wire 4 6 alu_control [3:0] $end
$var wire 1 7 RegWrite $end
$var wire 1 8 MemtoReg $end
$var wire 1 9 MemWrite $end
$var wire 1 : MemRead $end
$var wire 1 ; Branch $end
$var wire 32 < ALUSrc2 [31:0] $end
$var wire 1 = ALUSrc $end
$var wire 2 > ALUOp [1:0] $end
$scope module ALUSrc_mux $end
$var wire 32 ? entrada1 [31:0] $end
$var wire 32 @ entrada2 [31:0] $end
$var wire 1 ! seletor $end
$var wire 32 A saida [31:0] $end
$upscope $end
$scope module InstMem $end
$var wire 32 B instrucao [31:0] $end
$var wire 32 C endereco [31:0] $end
$upscope $end
$scope module alu $end
$var wire 32 D entrada2 [31:0] $end
$var wire 1 $ zero $end
$var wire 32 E entrada1 [31:0] $end
$var wire 4 F alu_control [3:0] $end
$var reg 32 G resultado [31:0] $end
$upscope $end
$scope module aluCtrl $end
$var wire 3 H funct3 [2:0] $end
$var wire 7 I funct7 [6:0] $end
$var wire 1 J funct7_5 $end
$var wire 2 K aluOp [1:0] $end
$var reg 4 L alu_control [3:0] $end
$upscope $end
$scope module ctrl $end
$var wire 7 M opcode [6:0] $end
$var reg 2 N ALUOp [1:0] $end
$var reg 1 = ALUSrc $end
$var reg 1 ; Branch $end
$var reg 1 : MemRead $end
$var reg 1 9 MemWrite $end
$var reg 1 8 MemtoReg $end
$var reg 1 7 RegWrite $end
$upscope $end
$scope module dataMem $end
$var wire 1 : MemRead $end
$var wire 1 9 MemWrite $end
$var wire 1 " clock $end
$var wire 32 O endereco [31:0] $end
$var wire 32 P write_data [31:0] $end
$var wire 32 Q read_data [31:0] $end
$upscope $end
$scope module immGen $end
$var wire 32 R instrucao [31:0] $end
$var wire 7 S opcode [6:0] $end
$var wire 3 T funct3 [2:0] $end
$var reg 32 U immediate [31:0] $end
$upscope $end
$scope module pc_reg $end
$var wire 1 " clock $end
$var wire 32 V pc_prox [31:0] $end
$var wire 1 # reset $end
$var reg 32 W pc [31:0] $end
$upscope $end
$scope module registradores $end
$var wire 1 7 RegWrite $end
$var wire 1 " clock $end
$var wire 5 X rd [4:0] $end
$var wire 5 Y rs1 [4:0] $end
$var wire 5 Z rs2 [4:0] $end
$var wire 32 [ write_data [31:0] $end
$var wire 32 \ read_data2 [31:0] $end
$var wire 32 ] read_data1 [31:0] $end
$var integer 32 ^ i [31:0] $end
$upscope $end
$scope module write_back_mux $end
$var wire 32 _ entrada1 [31:0] $end
$var wire 32 ` entrada2 [31:0] $end
$var wire 1 8 seletor $end
$var wire 32 a saida [31:0] $end
$upscope $end
$upscope $end
$upscope $end
$enddefinitions $end
#0
$dumpvars
b0 a
bz `
b0 _
b100000 ^
b0 ]
b0 \
b0 [
b1111 Z
b0 Y
b101 X
b0 W
b100 V
b1111 U
b0 T
b10011 S
b111100000000001010010011 R
bz Q
b0 P
b0 O
b0 N
b10011 M
b10 L
b0 K
0J
b0 I
b0 H
b0 G
b10 F
b0 E
b0 D
b0 C
b111100000000001010010011 B
b100 A
b1111 @
b100 ?
b0 >
0=
b0 <
0;
0:
09
08
07
b10 6
b0 5
b1111 4
b0 3
b0 2
b1111 1
b111100000000001010010011 0
bz /
b10011 .
b0 -
b100 ,
b100 +
b101 *
b0 )
b0 (
b0 '
b1111 &
b0 %
1$
1#
0"
0!
$end
#5000
1"
#10000
0"
0#
#15000
b101000000 1
b101000000 U
b1010 2
b1010 I
b0 &
b0 Z
b110 *
b110 X
b10100000000000000001100010011 0
b10100000000000000001100010011 B
b10100000000000000001100010011 R
b1000 +
b1000 A
b1000 V
b101000100 4
b101000100 @
b1000 ,
b1000 ?
b100 -
b100 C
b100 W
1"
#20000
0"
#25000
b1000 1
b1000 U
b0 2
b0 I
b1000 &
b1000 Z
b111 *
b111 X
b100000000000001110010011 0
b100000000000001110010011 B
b100000000000001110010011 R
b1100 +
b1100 A
b1100 V
b10000 4
b10000 @
b1100 ,
b1100 ?
b1000 -
b1000 C
b1000 W
1"
#30000
0"
#35000
1=
19
b0 1
b0 U
b100011 S
b10 T
b110 &
b110 Z
b111 '
b111 Y
b0 *
b0 X
b10 3
b10 H
b100011 .
b100011 M
b11000111010000000100011 0
b11000111010000000100011 B
b11000111010000000100011 R
b10000 +
b10000 A
b10000 V
b1100 4
b1100 @
b10000 ,
b10000 ?
b1100 -
b1100 C
b1100 W
1"
#40000
0"
#45000
1!
b110 6
b110 F
b110 L
b1 >
b1 K
b1 N
1;
0=
09
b100 1
b100 U
b1100011 S
b0 T
b101 '
b101 Y
b100 *
b100 X
b0 3
b0 H
b1100011 .
b1100011 M
b11000101000001001100011 0
b11000101000001001100011 B
b11000101000001001100011 R
b10100 +
b10100 A
b10100 V
b10100 4
b10100 @
b10100 ,
b10100 ?
b10000 -
b10000 C
b10000 W
1"
#50000
0"
#55000
b10 6
b10 F
b10 L
0!
b0 >
b0 K
b0 N
0;
b1 1
b1 U
b10011 S
b1 &
b1 Z
b101 *
b101 X
b10011 .
b10011 M
b100101000001010010011 0
b100101000001010010011 B
b100101000001010010011 R
b11000 +
b11000 A
b11000 V
b10101 4
b10101 @
b11000 ,
b11000 ?
b10100 -
b10100 C
b10100 W
1"
#60000
0"
#65000
b0 /
b0 Q
b0 `
1=
17
18
1:
b0 1
b0 U
b11 S
b10 T
b0 &
b0 Z
b111 '
b111 Y
b100 *
b100 X
b10 3
b10 H
b11 .
b11 M
b111010001000000011 0
b111010001000000011 B
b111010001000000011 R
b11100 +
b11100 A
b11100 V
b11000 4
b11000 @
b11100 ,
b11100 ?
b11000 -
b11000 C
b11000 W
1"
#70000
0"
#75000
1!
bz /
bz Q
bz `
b110 6
b110 F
b110 L
b1 >
b1 K
b1 N
1;
07
0=
08
0:
b100 1
b100 U
b1100011 S
b0 T
b110 &
b110 Z
b100 '
b100 Y
b0 3
b0 H
b1100011 .
b1100011 M
b11000100000001001100011 0
b11000100000001001100011 B
b11000100000001001100011 R
b100000 +
b100000 A
b100000 V
b100000 4
b100000 @
b100000 ,
b100000 ?
b11100 -
b11100 C
b11100 W
1"
#80000
0"
#85000
0!
b10 6
b10 F
b10 L
1J
b0 >
b0 K
b0 N
0;
b11000110000 1
b11000110000 U
b10011 S
b110001 2
b110001 I
b10000 &
b10000 Z
b0 '
b0 Y
b1 *
b1 X
b10011 .
b10011 M
b1100011000000000000000010010011 0
b1100011000000000000000010010011 B
b1100011000000000000000010010011 R
b100100 +
b100100 A
b100100 V
b11001010000 4
b11001010000 @
b100100 ,
b100100 ?
b100000 -
b100000 C
b100000 W
1"
#90000
0"
#95000
1!
b110 6
b110 F
b110 L
0J
b1 >
b1 K
b1 N
1;
b0 1
b0 U
b1100011 S
b0 2
b0 I
b0 &
b0 Z
b0 *
b0 X
b1100011 .
b1100011 M
b1100011 0
b1100011 B
b1100011 R
b100100 +
b100100 A
b100100 V
b100100 4
b100100 @
b101000 ,
b101000 ?
b100100 -
b100100 C
b100100 W
1"
