src/mux2.v
module mux2 #(parameter WIDTH = 32)(
    input wire seletor,
    input wire [WIDTH-1:0] entrada1,
    input wire [WIDTH-1:0] entrada2,
    output wire [WIDTH-1:0] saida
);
    assign saida = (seletor) ? entrada2 : entrada1;

endmodule

src/data_memory.v
module data_memory(
    input wire clock,
    input wire MemRead, MemWrite,
    input wire [31:0] endereco,
    input wire [31:0] write_data,
    output wire [31:0] read_data
);
    reg [31:0] memoria [0:255];

    assign read_data = MemRead ? memoria[endereco[9:2]] : 32'b0;

    always @(posedge clock) begin
        if (MemWrite) begin
            memoria[endereco[9:2]] <= write_data; 
        end
    end


endmodule

src/alu.v
module alu(
    input wire [31:0] entrada1,
    input wire [31:0] entrada2,
    input wire [3:0] alu_control,
    output reg [31:0] resultado,
    output wire zero
);

    assign zero = (resultado == 32'b0);
    
    always @(*) begin
        case (alu_control)
           4'b0010: resultado = entrada1 + entrada2;                // ADD
            4'b0110: resultado = entrada1 - entrada2;                // SUB
            4'b0000: resultado = entrada1 & entrada2;                // AND
            4'b0001: resultado = entrada1 | entrada2;                // OR
            4'b0100: resultado = entrada1 ^ entrada2;                // XOR
            4'b0101: resultado = ~(entrada1 | entrada2);             // NOR
            4'b0111: resultado = ($signed(entrada1) < $signed(entrada2)) ? 32'd1 : 32'd0; // SLT (se quiser)
            4'b1000: resultado = entrada1 << entrada2[4:0];          // SLL
            4'b1001: resultado = entrada1 >> entrada2[4:0];          // SRL
            default: resultado = 32'b0;
        endcase
    end

endmodule

src/alu_control.v
module alu_control(
    input wire [1:0] aluOp,
    input wire [2:0] funct3,
    input wire [6:0] funct7,
    output reg [3:0] alu_control
);
    
    always @(*) begin
        case (aluOp)
            2'b00: alu_control = 4'b0010; // Load/Store
            2'b01: alu_control = 4'b0110; // Branch
            2'b10: begin // R-type
                case ({funct7, funct3})
                    4'b0000: alu_control = 4'b0010; // ADD
                    4'b1000: alu_control = 4'b0110; // SUB
                    4'b0001: alu_control = 4'b0000; // SLL
                    4'b0010: alu_control = 4'b0001; // SLT
                    4'b0100: alu_control = 4'b0001; // XOR
                    4'b0110: alu_control = 4'b0000; // OR
                    default: alu_control = 4'b1111; // Invalid operation
                endcase
            end
            default: alu_control = 4'b1111; // Invalid operation
        endcase
    end
endmodule

src/imm_gen.v
module imm_gen(
    input wire [31:0] instrucao,
    output reg [31:0] immediate
);

wire [6:0] opcode = instrucao[6:0];
wire [2:0] funct3 = instrucao[14:12];

always @(*) begin
        case (opcode)
            7'b0000011, // LW
            7'b0010011: // I-type
                immediate = {{20{instrucao[31]}}, instrucao[31:20]};
            7'b0100011: // SW
                immediate = {{20{instrucao[31]}}, instrucao[31:25], instrucao[11:7]};

            7'b1100011: // BEQ
                immediate = {{19{instrucao[31]}}, instrucao[31], instrucao[7],
                             instrucao[30:25], instrucao[11:8], 1'b0};

            default:
                immediate = 0;
        endcase
    end

endmodule

src/register.v
module register(
    input wire clock, RegWrite,
    input wire [4:0] rs1, rs2, rd,
    input wire [31:0] write_data,
    output wire [31:0] read_data1, read_data2
);
    reg [31:0] registradores [0:31];

    assign read_data1 = (rs1 == 5'd0) ? 32'b0 : registradores[rs1];
    assign read_data2 = (rs2 == 5'd0) ? 32'b0 : registradores[rs2];

    always @(posedge clock) begin
        if (RegWrite && rd != 0) begin
            registradores[rd] <= write_data;
        end
    end

endmodule

src/control.v
module control(
    input wire [6:0] opcode,
    output reg Branch, MemRead, MemWrite, ALUSrc, RegWrite,
    output reg MemtoReg,
    output reg [1:0] ALUOp    
);

    always @(*) begin
        Branch = 1'b0;
        MemRead = 1'b0;
        MemWrite = 1'b0;
        ALUSrc = 1'b0;
        RegWrite = 1'b0;
        MemtoReg = 1'b0;
        ALUOp = 2'b00;
        
        case(opcode)
            7'b0110011: begin // R-type
                RegWrite = 1'b1;
                ALUOp = 2'b10;
                ALUSrc = 1'b0;
            end
            7'b0100011: begin // S-type
                MemWrite = 1'b1;
                ALUSrc = 1'b1;
                ALUOp = 2'b00;
            end
            7'b1100011: begin // B-type
                Branch = 1'b1;
                ALUOp = 2'b01;
                ALUSrc = 1'b0;
            end
            7'b0110111: begin // U-type - LUI
                RegWrite = 1'b1;
                ALUSrc = 1'b0;
            end
            7'b1101111: begin // J-type - JAL
                RegWrite = 1'b1;
                Branch = 1'b1;
                MemtoReg = 1'b0;
            end
            7'b0000011: begin // I-type - load
                RegWrite = 1'b1;
                MemRead = 1'b1;
                MemtoReg = 1'b1;
                ALUSrc = 1'b1;
                ALUOp = 2'b00;
            end
            7'b0010011: begin // I-type - immediate arithmetic
                RegWrite = 1'b1;
                ALUSrc = 1'b1;
                ALUOp = 2'b00;
            end
            default: begin
            end
        endcase
    end

endmodule

src/instruction_memory.v
module instruction_memory(
    input wire [31:0]endereco,
    output wire [31:0] instrucao
);
    reg [31:0] memoria [0:9];

    initial begin
        $readmemb("programa.bin", memoria);
    end

    assign instrucao = memoria[endereco[9:2]];
endmodule

src/pc.v
module pc(
    input wire clock,
    input wire reset,
    input wire [31:0] pc_prox,
    output reg [31:0] pc
);

    always @(posedge clock or posedge reset) begin
        if (reset)
            pc <= 0;
        else
            pc <= pc_prox;
    end

endmodule

src/cpu.v
module cpu (
    input wire clock,
    input wire reset
);

    // PC e Instrução
    wire [31:0] pc, pc_prox, pc_plus4;
    wire [31:0] instrucao;

    assign pc_plus4 = pc + 32'd4;

    pc pc_reg(
        .clock(clock),
        .reset(reset),
        .pc_prox(pc_prox),
        .pc(pc)
    );

    instruction_memory InstMem (
        .endereco(pc),
        .instrucao(instrucao)
    );

    // Decodificação
    wire [6:0] opcode = instrucao[6:0];
    wire [4:0] rd     = instrucao[11:7];
    wire [2:0] funct3 = instrucao[14:12];
    wire [4:0] rs1    = instrucao[19:15];
    wire [4:0] rs2    = instrucao[24:20];
    wire [6:0] funct7 = instrucao[31:25];

    wire [31:0] read_data1, read_data2;
    wire [31:0] immediate;

    wire Branch, MemRead, MemWrite, ALUSrc, RegWrite;
    wire MemtoReg;
    wire [1:0] ALUOp; 


    control ctrl(
        .opcode(opcode),
        .Branch(Branch),
        .MemRead(MemRead),
        .MemtoReg(MemtoReg),
        .MemWrite(MemWrite),
        .ALUSrc(ALUSrc),
        .RegWrite(RegWrite),
        .ALUOp(ALUOp)
    );

    register registradores(
        .clock(clock),
        .RegWrite(RegWrite),
        .rs1(rs1),
        .rs2(rs2),
        .rd(rd),
        .write_data(write_back_data),
        .read_data1(read_data1),
        .read_data2(read_data2)
    );

    imm_gen immGen(
        .instrucao(instrucao),
        .immediate(immediate)
    );

    // ALU
    wire [3:0] alu_control;
    wire [31:0] alu_entrada2 = ALUSrc ? immediate : read_data2;
    wire [31:0] alu_result;
    wire zero;

    alu_control aluCtrl(
        .aluOp(ALUOp),
        .funct3(funct3),
        .funct7(funct7),
        .alu_control(alu_control)
    );

    alu alu(
        .entrada1(read_data1),
        .entrada2(alu_entrada2),
        .alu_control(alu_control),
        .resultado(alu_result),
        .zero(zero)
    );

    // Memória de Dados
    wire [31:0] MemRead_data;

    data_memory dataMem(
        .clock(clock),
        .MemRead(MemRead),
        .MemWrite(MemWrite),
        .endereco(alu_result),
        .write_data(read_data2),
        .read_data(MemRead_data)
    );

    // Write Back
    wire [31:0] write_back_data;

    mux2 #(.WIDTH(32)) write_back_mux(
        .seletor(MemtoReg),
        .entrada1(alu_result),
        .entrada2(MemRead_data),
        .saida(write_back_data)
    );

    // Controle de Desvio (Branch)
    wire [31:0] branch_alvo = pc + immediate;
    wire branch_taken = Branch & zero;

    mux2 #(.WIDTH(32)) pc_mux(
        .seletor(branch_taken),
        .entrada1(pc_plus4),
        .entrada2(branch_alvo),
        .saida(pc_prox)
    );

endmodule

src/testbench.v
`timescale 1ns/1ps

module testbench;

    reg clock;
    reg reset;

    cpu uut (
        .clock(clock),
        .reset(reset)
    );

    integer errors;

    initial begin
        $dumpfile("testbench.vcd");
        $dumpvars(0, uut);

        
        clock = 0;
        reset = 1;
        errors = 0;

        #10;
        reset = 0;

        #100;

        $display("=== Resultado do Testbench: ===");

        

        $display("x1 = %d", uut.registradores.registradores[1]);
        $display("x4 = %d", uut.registradores.registradores[4]);
        $display("x5 = %d", uut.registradores.registradores[5]);
        $display("x6 = %d", uut.registradores.registradores[6]);
        $display("x7 = %d", uut.registradores.registradores[7]);
        $display("Data Memory[1] =%d", uut.dataMem.memoria[1]);

        $finish;
    end

   always begin
        #5 clock = ~clock; // Toggle clock every 5 time units
    end
endmodule

src/testbench.vcd
$date
	Thu Aug 07 20:25:53 2025
$end
$version
	Icarus Verilog
$end
$timescale
	1ps
$end
$scope module testbench $end
$scope module uut $end
$var wire 1 ! branch_taken $end
$var wire 1 " clock $end
$var wire 1 # reset $end
$var wire 1 $ zero $end
$var wire 32 % write_back_data [31:0] $end
$var wire 5 & rs2 [4:0] $end
$var wire 5 ' rs1 [4:0] $end
$var wire 32 ( read_data2 [31:0] $end
$var wire 32 ) read_data1 [31:0] $end
$var wire 5 * rd [4:0] $end
$var wire 32 + pc_prox [31:0] $end
$var wire 32 , pc_plus4 [31:0] $end
$var wire 32 - pc [31:0] $end
$var wire 7 . opcode [6:0] $end
$var wire 32 / instrucao [31:0] $end
$var wire 32 0 immediate [31:0] $end
$var wire 7 1 funct7 [6:0] $end
$var wire 3 2 funct3 [2:0] $end
$var wire 32 3 branch_alvo [31:0] $end
$var wire 32 4 alu_result [31:0] $end
$var wire 32 5 alu_entrada2 [31:0] $end
$var wire 4 6 alu_control [3:0] $end
$var wire 1 7 RegWrite $end
$var wire 1 8 MemtoReg $end
$var wire 1 9 MemWrite $end
$var wire 32 : MemRead_data [31:0] $end
$var wire 1 ; MemRead $end
$var wire 1 < Branch $end
$var wire 1 = ALUSrc $end
$var wire 2 > ALUOp [1:0] $end
$scope module InstMem $end
$var wire 32 ? instrucao [31:0] $end
$var wire 32 @ endereco [31:0] $end
$upscope $end
$scope module alu $end
$var wire 32 A entrada2 [31:0] $end
$var wire 1 $ zero $end
$var wire 32 B entrada1 [31:0] $end
$var wire 4 C alu_control [3:0] $end
$var reg 32 D resultado [31:0] $end
$upscope $end
$scope module aluCtrl $end
$var wire 3 E funct3 [2:0] $end
$var wire 7 F funct7 [6:0] $end
$var wire 2 G aluOp [1:0] $end
$var reg 4 H alu_control [3:0] $end
$upscope $end
$scope module ctrl $end
$var wire 7 I opcode [6:0] $end
$var reg 2 J ALUOp [1:0] $end
$var reg 1 = ALUSrc $end
$var reg 1 < Branch $end
$var reg 1 ; MemRead $end
$var reg 1 9 MemWrite $end
$var reg 1 8 MemtoReg $end
$var reg 1 7 RegWrite $end
$upscope $end
$scope module dataMem $end
$var wire 1 ; MemRead $end
$var wire 1 9 MemWrite $end
$var wire 1 " clock $end
$var wire 32 K endereco [31:0] $end
$var wire 32 L write_data [31:0] $end
$var wire 32 M read_data [31:0] $end
$upscope $end
$scope module immGen $end
$var wire 32 N instrucao [31:0] $end
$var wire 7 O opcode [6:0] $end
$var wire 3 P funct3 [2:0] $end
$var reg 32 Q immediate [31:0] $end
$upscope $end
$scope module pc_mux $end
$var wire 32 R entrada1 [31:0] $end
$var wire 32 S entrada2 [31:0] $end
$var wire 1 ! seletor $end
$var wire 32 T saida [31:0] $end
$upscope $end
$scope module pc_reg $end
$var wire 1 " clock $end
$var wire 32 U pc_prox [31:0] $end
$var wire 1 # reset $end
$var reg 32 V pc [31:0] $end
$upscope $end
$scope module registradores $end
$var wire 1 7 RegWrite $end
$var wire 1 " clock $end
$var wire 5 W rd [4:0] $end
$var wire 5 X rs1 [4:0] $end
$var wire 5 Y rs2 [4:0] $end
$var wire 32 Z write_data [31:0] $end
$var wire 32 [ read_data2 [31:0] $end
$var wire 32 \ read_data1 [31:0] $end
$upscope $end
$scope module write_back_mux $end
$var wire 32 ] entrada1 [31:0] $end
$var wire 32 ^ entrada2 [31:0] $end
$var wire 1 8 seletor $end
$var wire 32 _ saida [31:0] $end
$upscope $end
$upscope $end
$upscope $end
$enddefinitions $end
#0
$dumpvars
b1111 _
b0 ^
b1111 ]
b0 \
bx [
b1111 Z
b1111 Y
b0 X
b101 W
b0 V
b100 U
b100 T
b1111 S
b100 R
b1111 Q
b0 P
b10011 O
b111100000000001010010011 N
b0 M
bx L
b1111 K
b0 J
b10011 I
b10 H
b0 G
b0 F
b0 E
b1111 D
b10 C
b0 B
b1111 A
b0 @
b111100000000001010010011 ?
b0 >
1=
0<
0;
b0 :
09
08
17
b10 6
b1111 5
b1111 4
b1111 3
b0 2
b0 1
b1111 0
b111100000000001010010011 /
b10011 .
b0 -
b100 ,
b100 +
b101 *
b0 )
bx (
b0 '
b1111 &
b1111 %
0$
1#
0"
0!
$end
#5000
1"
#10000
0"
0#
#15000
b101000000 %
b101000000 Z
b101000000 _
b101000000 4
b101000000 D
b101000000 K
b101000000 ]
b101000000 5
b101000000 A
b0 (
b0 L
b0 [
b101000000 0
b101000000 Q
b1010 1
b1010 F
b0 &
b0 Y
b110 *
b110 W
b10100000000000000001100010011 /
b10100000000000000001100010011 ?
b10100000000000000001100010011 N
b1000 +
b1000 T
b1000 U
b101000100 3
b101000100 S
b1000 ,
b1000 R
b100 -
b100 @
b100 V
1"
#20000
0"
#25000
b1000 %
b1000 Z
b1000 _
b1000 4
b1000 D
b1000 K
b1000 ]
b1000 5
b1000 A
bx (
bx L
bx [
b1000 0
b1000 Q
b0 1
b0 F
b1000 &
b1000 Y
b111 *
b111 W
b100000000000001110010011 /
b100000000000001110010011 ?
b100000000000001110010011 N
b1100 +
b1100 T
b1100 U
b10000 3
b10000 S
b1100 ,
b1100 R
b1000 -
b1000 @
b1000 V
1"
#30000
0"
#35000
b0 5
b0 A
b101000000 (
b101000000 L
b101000000 [
b1000 )
b1000 B
b1000 \
19
07
1=
b0 0
b0 Q
b100011 O
b10 P
b110 &
b110 Y
b111 '
b111 X
b10 2
b10 E
b0 *
b0 W
b100011 .
b100011 I
b11000111010000000100011 /
b11000111010000000100011 ?
b11000111010000000100011 N
b10000 +
b10000 T
b10000 U
b1100 3
b1100 S
b10000 ,
b10000 R
b1100 -
b1100 @
b1100 V
1"
#40000
0"
#45000
b11111111111111111111111011001111 %
b11111111111111111111111011001111 Z
b11111111111111111111111011001111 _
b11111111111111111111111011001111 4
b11111111111111111111111011001111 D
b11111111111111111111111011001111 K
b11111111111111111111111011001111 ]
b101000000 5
b101000000 A
b1111 )
b1111 B
b1111 \
b110 6
b110 C
b110 H
b1 >
b1 G
b1 J
1<
0=
09
b100 0
b100 Q
b1100011 O
b0 P
b101 '
b101 X
b0 2
b0 E
b100 *
b100 W
b1100011 .
b1100011 I
b11000101000001001100011 /
b11000101000001001100011 ?
b11000101000001001100011 N
b10100 +
b10100 T
b10100 U
b10100 3
b10100 S
b10100 ,
b10100 R
b10000 -
b10000 @
b10000 V
1"
#50000
0"
#55000
b10000 %
b10000 Z
b10000 _
b10000 4
b10000 D
b10000 K
b10000 ]
b1 5
b1 A
b10 6
b10 C
b10 H
bx (
bx L
bx [
1=
17
b0 >
b0 G
b0 J
0<
b1 0
b1 Q
b10011 O
b1 &
b1 Y
b101 *
b101 W
b10011 .
b10011 I
b100101000001010010011 /
b100101000001010010011 ?
b100101000001010010011 N
b11000 +
b11000 T
b11000 U
b10101 3
b10101 S
b11000 ,
b11000 R
b10100 -
b10100 @
b10100 V
1"
#60000
0"
#65000
b101000000 :
b101000000 M
b101000000 ^
b101000000 %
b101000000 Z
b101000000 _
b0 5
b0 A
b0 (
b0 L
b0 [
18
1;
17
1=
b1000 4
b1000 D
b1000 K
b1000 ]
b0 0
b0 Q
b11 O
b10 P
b0 &
b0 Y
b111 '
b111 X
b10 2
b10 E
b100 *
b100 W
b11 .
b11 I
b1000 )
b1000 B
b1000 \
b111010001000000011 /
b111010001000000011 ?
b111010001000000011 N
b11100 +
b11100 T
b11100 U
b11000 3
b11000 S
b11100 ,
b11100 R
b11000 -
b11000 @
b11000 V
1"
#70000
0"
#75000
1!
1$
b0 4
b0 D
b0 K
b0 ]
b0 %
b0 Z
b0 _
b0 :
b0 M
b0 ^
b101000000 5
b101000000 A
b101000000 (
b101000000 L
b101000000 [
b101000000 )
b101000000 B
b101000000 \
b110 6
b110 C
b110 H
b1 >
b1 G
b1 J
1<
08
07
0=
0;
b100 0
b100 Q
b1100011 O
b0 P
b110 &
b110 Y
b100 '
b100 X
b0 2
b0 E
b1100011 .
b1100011 I
b11000100000001001100011 /
b11000100000001001100011 ?
b11000100000001001100011 N
b100000 +
b100000 T
b100000 U
b100000 3
b100000 S
b100000 ,
b100000 R
b11100 -
b11100 @
b11100 V
1"
#80000
0"
#85000
b11000110000 %
b11000110000 Z
b11000110000 _
0$
b11000110000 4
b11000110000 D
b11000110000 K
b11000110000 ]
b11000110000 5
b11000110000 A
0!
b10 6
b10 C
b10 H
bx (
bx L
bx [
b0 )
b0 B
b0 \
1=
17
b0 >
b0 G
b0 J
0<
b11000110000 0
b11000110000 Q
b10011 O
b110001 1
b110001 F
b10000 &
b10000 Y
b0 '
b0 X
b1 *
b1 W
b10011 .
b10011 I
b1100011000000000000000010010011 /
b1100011000000000000000010010011 ?
b1100011000000000000000010010011 N
b100100 +
b100100 T
b100100 U
b11001010000 3
b11001010000 S
b100100 ,
b100100 R
b100000 -
b100000 @
b100000 V
1"
#90000
0"
#95000
1!
b0 %
b0 Z
b0 _
1$
b0 4
b0 D
b0 K
b0 ]
b0 5
b0 A
b110 6
b110 C
b110 H
b0 (
b0 L
b0 [
b1 >
b1 G
b1 J
1<
07
0=
b0 0
b0 Q
b1100011 O
b0 1
b0 F
b0 &
b0 Y
b0 *
b0 W
b1100011 .
b1100011 I
b1100011 /
b1100011 ?
b1100011 N
b100100 +
b100100 T
b100100 U
b100100 3
b100100 S
b101000 ,
b101000 R
b100100 -
b100100 @
b100100 V
1"
