src/mux2.v
module mux2 #(parameter WIDTH = 32)(
    input wire seletor,
    input wire [WIDTH-1:0] entrada1,
    input wire [WIDTH-1:0] entrada2,
    output wire [WIDTH-1:0] saida
);
    assign saida = (seletor) ? entrada2 : entrada1;

endmodule

src/data_memory.v
module data_memory(
    input logic clock,
    input logic MemRead, MemWrite,
    input logic [31:0] endereco,
    input logic [31:0] write_data,
    output logic [31:0] read_data
);
    logic [31:0] memory [0:255];

    assign read_data = (MemRead) ? memory[endereco[9:2]] : 0; // Read data from the specified endereco

    always_ff @(posedge clock) begin
        if (MemWrite) begin
            memory[endereco[9:2]] <= write_data; // Write data to the specified endereco
        end
    end

endmodule

src/alu.v
module alu(
    input wire [31:0] entrada1,
    input wire [31:0] entrada2,
    input wire [3:0] alu_control,
    output reg [31:0] resultado,
    output wire zero
);

    assign zero = (resultado == 32'b0);

    always @(*) begin
        case (alu_control)
            4'b0000: resultado = entrada1 + entrada2;                               // ADD
            4'b0001: resultado = entrada1 - entrada2;                               // SUB
            4'b0010: resultado = entrada1 & entrada2;                               // AND
            4'b0011: resultado = entrada1 | entrada2;                               // OR
            4'b0100: resultado = entrada1 ^ entrada2;                               // XOR
            4'b0101: resultado = ~(entrada1 | entrada2);                            // NOR
            4'b0110: resultado = ($signed(entrada1) < $signed(entrada2)) ? 32'd1 : 32'd0; // SLT signed
            4'b0111: resultado = (entrada1 < entrada2) ? 32'd1 : 32'd0;              // SLT unsigned
            4'b1000: resultado = entrada1 << entrada2[4:0];                         // SLL
            4'b1001: resultado = entrada1 >> entrada2[4:0];                         // SRL
            4'b1010: resultado = $signed(entrada1) >>> entrada2[4:0];               // SRA
            default: resultado = 32'b0;
        endcase
    end

endmodule

src/alu_control.v
module alu_control(
    input  wire [1:0] ALUOp,      // vem do control unit
    input  wire [2:0] funct3,     // instrução
    input  wire [6:0] funct7,     // instrução (usamos bit[5] para distinguir SRL/SRA e ADD/SUB)
    output reg  [3:0] alu_control // código para a ALU
);

    always @(*) begin
        // default
        alu_control = 4'b0000; // ADD por padrão

        case (ALUOp)
            2'b00: begin
                // Tipicamente usado para loads/stores (ADD) e instruções I-type
                case (funct3)
                    3'b000: alu_control = 4'b0000; // ADD / ADDI / LW / SW
                    3'b001: alu_control = 4'b1000; // SLLI
                    3'b010: alu_control = 4'b0110; // SLTI (signed)
                    3'b011: alu_control = 4'b0111; // SLTIU (unsigned)
                    3'b100: alu_control = 4'b0100; // XORI
                    3'b101: begin                   // SRLI / SRAI (depende de funct7[5])
                        if (funct7[5]) alu_control = 4'b1010; // SRAI
                        else           alu_control = 4'b1001; // SRLI
                    end
                    3'b110: alu_control = 4'b0011; // ORI
                    3'b111: alu_control = 4'b0010; // ANDI
                    default: alu_control = 4'b0000;
                endcase
            end

            2'b01: begin
                // Branches — normalmente comparam usando SUB (BEQ/BNE) e outros sinais externos interpretam resultado
                alu_control = 4'b0001; // SUB
            end

            2'b10: begin
                // R-type: usar funct3 e funct7
                case (funct3)
                    3'b000: begin
                        // ADD or SUB (funct7 = 0100000 indica SUB em RV32)
                        if (funct7 == 7'b0100000) alu_control = 4'b0001; // SUB
                        else                      alu_control = 4'b0000; // ADD
                    end
                    3'b001: alu_control = 4'b1000; // SLL
                    3'b010: alu_control = 4'b0110; // SLT (signed)
                    3'b011: alu_control = 4'b0111; // SLTU (unsigned)
                    3'b100: alu_control = 4'b0100; // XOR
                    3'b101: begin
                        // SRL or SRA (funct7[5] == 1 -> SRA)
                        if (funct7[5]) alu_control = 4'b1010; // SRA
                        else           alu_control = 4'b1001; // SRL
                    end
                    3'b110: alu_control = 4'b0011; // OR
                    3'b111: alu_control = 4'b0010; // AND
                    default: alu_control = 4'b0000;
                endcase
            end

            default: begin
                // segurança: ADD por padrão
                alu_control = 4'b0000;
            end
        endcase
    end

endmodule

src/imm_gen.v
module imm_gen (
    input  wire [31:0] instrucao,
    output reg  [31:0] imm_out
);

    wire [6:0] opcode = instrucao[6:0];

    always @(*) begin
        case (opcode)
            // I-type (ex.: addi, lw, jalr)
            7'b0000011, // LW
            7'b0010011, // ADDI
            7'b1100111: // JALR
                imm_out = {{20{instrucao[31]}}, instrucao[31:20]};

            // S-type (ex.: sw)
            7'b0100011:
                imm_out = {{20{instrucao[31]}}, instrucao[31:25], instrucao[11:7]};

            // B-type (ex.: beq, bne)
            7'b1100011:
                imm_out = {{19{instrucao[31]}}, instrucao[31], instrucao[7],
                           instrucao[30:25], instrucao[11:8], opcode};

            // U-type (ex.: lui, auipc)
            7'b0110111, // LUI
            7'b0010111: // AUIPC
                imm_out = {instrucao[31:12], 12'b0};

            // J-type (ex.: jal)
            7'b1101111:
                imm_out = {{11{instrucao[31]}}, instrucao[31],
                           instrucao[19:12], instrucao[20],
                           instrucao[30:21], 1'b0};

            // Default (R-type ou instrução inválida)
            default:
                imm_out = 32'b0;
        endcase
    end

endmodule

src/register.v
module register(
    input wire clock, RegWrite,
    input wire [4:0] rs1, rs2, rd,
    input wire [31:0] write_data,
    output reg [31:0] read_data1, read_data2
);
    reg [31:0] registradores [0:31];
    integer i;

    initial begin
        for (i = 0; i < 32; i = i + 1) begin
            registradores[i] = 32'b0;
        end
    end

    always @(posedge clock) begin
        if (RegWrite && rd != 0) begin
            registradores[rd] <= write_data;
        end
    end

    always @(*) begin
        read_data1 = (rs1 == 0) ? 0 : registradores[rs1];
        read_data2 = (rs2 == 0) ? 0 : registradores[rs2];
    end

endmodule

src/control.v
module control(
    input wire [6:0] opcode,
    output reg Branch, MemRead, MemtoReg, MemWrite, ALUSrc, RegWrite,
    output logic [1:0] ALUOp    
);

    always @(*) begin
        Branch = 1'b0;
        MemRead = 1'b0;
        MemtoReg = 1'b0;
        MemWrite = 1'b0;
        ALUSrc = 1'b0;
        RegWrite = 1'b0;
        ALUOp = 2'b00;
        
        case(opcode)
            7'b0110011: begin // R-type
                RegWrite = 1'b1;
                ALUOp = 2'b10;
                ALUSrc = 1'b0;
                MemtoReg = 1'b0;
            end
            7'b0000011: begin // Load
                MemRead = 1'b1;
                MemtoReg = 1'b1;
                RegWrite = 1'b1;
                ALUSrc = 1'b1;
                ALUOp = 2'b00;
            end
            7'b0100011: begin // Store
                MemWrite = 1'b1;
                ALUSrc = 1'b1;
                ALUOp = 2'b00;
            end
            7'b1100011: begin // Branch
                Branch = 1'b1;
                ALUOp = 2'b01;
                ALUSrc = 1'b0;
            end
           default: begin
           end
        endcase
    end

endmodule

src/instruction_memory.v
module instruction_memory(
    input wire [31:0]endereco,
    output wire [31:0] instrucao
);
    reg [31:0] memoria [0:9];

    initial $readmemb("programa.bin", memoria);

    assign instrucao = memoria[endereco[9:2]];
endmodule

src/pc.v
module pc(
    input wire clock,
    input wire reset,
    input wire [31:0] pc_prox,
    output reg [31:0] pc
);

    always @(posedge clock or posedge reset) begin
        if (reset)
            pc <= 0;
        else
            pc <= pc_prox;
    end

endmodule

src/cpu.v
module cpu (
    input wire clock,
    input wire reset
);

    // PC e Instrução
    wire [31:0] pc, pc_prox, pc_plus4;
    wire [31:0] instrucao;

    assign pc_plus4 = pc + 32'd4;

    pc pc_reg(
        .clock(clock),
        .reset(reset),
        .pc_prox(pc_prox),
        .pc(pc)
    );

    instruction_memory InstMem (
        .endereco(pc),
        .instrucao(instrucao)
    );

    // Decodificação
    wire [6:0] opcode = instrucao[6:0];
    wire [4:0] rd     = instrucao[11:7];
    wire [2:0] funct3 = instrucao[14:12];
    wire [4:0] rs1    = instrucao[19:15];
    wire [4:0] rs2    = instrucao[24:20];
    wire [6:0] funct7 = instrucao[31:25];

    wire [31:0] read_data1, read_data2;
    wire [31:0] immediate;

    wire Branch, MemRead, MemWrite, ALUSrc, RegWrite;
    wire MemtoReg;
    wire [1:0] ALUOp; 

    control ctrl(
        .opcode(opcode),
        .Branch(Branch),
        .MemRead(MemRead),
        .MemtoReg(MemtoReg),
        .MemWrite(MemWrite),
        .ALUSrc(ALUSrc),
        .RegWrite(RegWrite),
        .ALUOp(ALUOp)
    );

    register registradores(
        .clock(clock),
        .RegWrite(RegWrite),
        .rs1(rs1),
        .rs2(rs2),
        .rd(rd),
        .write_data(write_back_data),
        .read_data1(read_data1),
        .read_data2(read_data2)
    );

    imm_gen immGen(
        .instrucao(instrucao),
        .imm_out(immediate)
    );

    // ALU
    wire [3:0] alu_control;
    wire [31:0] alu_entrada2 = ALUSrc ? immediate : read_data2;
    wire [31:0] alu_result;
    wire zero;

    alu_control aluCtrl(
        .ALUOp(ALUOp),
        .funct3(funct3),
        .funct7(funct7),
        .alu_control(alu_control)
    );

    alu alu(
        .entrada1(read_data1),
        .entrada2(alu_entrada2),
        .alu_control(alu_control),
        .resultado(alu_result),
        .zero(zero)
    );

    // Memória de Dados
    wire [31:0] MemRead_data;

    data_memory dataMem(
        .clock(clock),
        .MemRead(MemRead),
        .MemWrite(MemWrite),
        .endereco(alu_result),
        .write_data(read_data2),
        .read_data(MemRead_data)
    );

    // Write Back
    wire [31:0] write_back_data;

    mux2 #(.WIDTH(32)) write_back_mux(
        .seletor(MemtoReg),
        .entrada1(alu_result),
        .entrada2(MemRead_data),
        .saida(write_back_data)
    );

    // Controle de Desvio (Branch)
    wire [31:0] branch_alvo = pc + immediate;
    wire branch_taken = Branch & zero;

    mux2 #(.WIDTH(32)) pc_mux(
        .seletor(branch_taken),
        .entrada1(pc_plus4),
        .entrada2(branch_alvo),
        .saida(pc_prox)
    );

    // ===== DEBUG =====
    integer i;
    always @(posedge clock) begin
        if (!reset) begin
            $display("\n=== Ciclo %d===", i);
            $display("PC=%0d Instrucao=%h", pc, instrucao);
            $display("opcode=%b funct3=%b funct7=%b rs1=%0d rs2=%0d rd=%0d", opcode, funct3, funct7, rs1, rs2, rd);
            $display("ALUOp=%b alu_control=%b", ALUOp, alu_control);
            $display("read_data1=%0d read_data2=%0d immediate=%0d", read_data1, read_data2, immediate);
            $display("ALU entrada1=%0d entrada2=%0d resultado=%0d zero=%b", read_data1, alu_entrada2, alu_result, zero);
            $display("Branch=%b MemRead=%b MemWrite=%b ALUSrc=%b RegWrite=%b MemtoReg=%b", Branch, MemRead, MemWrite, ALUSrc, RegWrite, MemtoReg);
            if (MemWrite)
                $display("** Escrevendo na Memoria: endereco=%0d dado=%0d", alu_result, read_data2);
            if (MemRead)
                $display("** Lendo da Memoria: endereco=%0d dado=%0d", alu_result, MemRead_data);
        end
    end

endmodule

src/testbench.v
`timescale 1ns/1ps

module testbench;

    reg clock;
    reg reset;

    cpu uut (
        .clock(clock),
        .reset(reset)
    );

    integer errors;

    initial begin
        $dumpfile("testbench.vcd");
        $dumpvars(0, uut);

        
        clock = 0;
        reset = 1;
        errors = 0;

        #10;
        reset = 0;

        #50;

        $display("=== Resultado do Testbench: ===");

        

        $display("x2 = %d", uut.registradores.registradores[2]);
        $display("x3 = %d", uut.registradores.registradores[3]);
        $display("x4 = %d", uut.registradores.registradores[4]);
        $display("x7 = %d", uut.registradores.registradores[7]);
        $display("x7 = %d", uut.registradores.registradores[7]);
        $display("Data Memory[0] =%d", uut.dataMem.memoria[2]);

        $finish;
    end

   always begin
        #5 clock = ~clock; // Toggle clock every 5 time units
    end
endmodule

src/testbench.vcd
$date
	Fri Aug 08 21:01:17 2025
$end
$version
	Icarus Verilog
$end
$timescale
	1ps
$end
$scope module testbench $end
$scope module uut $end
$var wire 1 ! branch_taken $end
$var wire 1 " clock $end
$var wire 1 # reset $end
$var wire 1 $ zero $end
$var wire 32 % write_back_data [31:0] $end
$var wire 5 & rs2 [4:0] $end
$var wire 5 ' rs1 [4:0] $end
$var wire 32 ( read_data2 [31:0] $end
$var wire 32 ) read_data1 [31:0] $end
$var wire 5 * rd [4:0] $end
$var wire 32 + pc_prox [31:0] $end
$var wire 32 , pc_plus4 [31:0] $end
$var wire 32 - pc [31:0] $end
$var wire 7 . opcode [6:0] $end
$var wire 32 / instrucao [31:0] $end
$var wire 32 0 immediate [31:0] $end
$var wire 7 1 funct7 [6:0] $end
$var wire 3 2 funct3 [2:0] $end
$var wire 32 3 branch_alvo [31:0] $end
$var wire 32 4 alu_result [31:0] $end
$var wire 32 5 alu_entrada2 [31:0] $end
$var wire 4 6 alu_control [3:0] $end
$var wire 1 7 RegWrite $end
$var wire 1 8 MemtoReg $end
$var wire 1 9 MemWrite $end
$var wire 32 : MemRead_data [31:0] $end
$var wire 1 ; MemRead $end
$var wire 1 < Branch $end
$var wire 1 = ALUSrc $end
$var wire 2 > ALUOp [1:0] $end
$var integer 32 ? i [31:0] $end
$scope module InstMem $end
$var wire 32 @ instrucao [31:0] $end
$var wire 32 A endereco [31:0] $end
$upscope $end
$scope module alu $end
$var wire 32 B entrada2 [31:0] $end
$var wire 1 $ zero $end
$var wire 32 C entrada1 [31:0] $end
$var wire 4 D alu_control [3:0] $end
$var reg 32 E resultado [31:0] $end
$upscope $end
$scope module aluCtrl $end
$var wire 3 F funct3 [2:0] $end
$var wire 7 G funct7 [6:0] $end
$var wire 2 H ALUOp [1:0] $end
$var reg 4 I alu_control [3:0] $end
$upscope $end
$scope module ctrl $end
$var wire 7 J opcode [6:0] $end
$var reg 2 K ALUOp [1:0] $end
$var reg 1 = ALUSrc $end
$var reg 1 < Branch $end
$var reg 1 ; MemRead $end
$var reg 1 9 MemWrite $end
$var reg 1 8 MemtoReg $end
$var reg 1 7 RegWrite $end
$upscope $end
$scope module dataMem $end
$var wire 1 ; MemRead $end
$var wire 1 9 MemWrite $end
$var wire 1 " clock $end
$var wire 32 L endereco [31:0] $end
$var wire 32 M write_data [31:0] $end
$var wire 32 N read_data [31:0] $end
$upscope $end
$scope module immGen $end
$var wire 32 O instrucao [31:0] $end
$var wire 7 P opcode [6:0] $end
$var reg 32 Q imm_out [31:0] $end
$upscope $end
$scope module pc_mux $end
$var wire 32 R entrada1 [31:0] $end
$var wire 32 S entrada2 [31:0] $end
$var wire 1 ! seletor $end
$var wire 32 T saida [31:0] $end
$upscope $end
$scope module pc_reg $end
$var wire 1 " clock $end
$var wire 32 U pc_prox [31:0] $end
$var wire 1 # reset $end
$var reg 32 V pc [31:0] $end
$upscope $end
$scope module registradores $end
$var wire 1 7 RegWrite $end
$var wire 1 " clock $end
$var wire 5 W rd [4:0] $end
$var wire 5 X rs1 [4:0] $end
$var wire 5 Y rs2 [4:0] $end
$var wire 32 Z write_data [31:0] $end
$var reg 32 [ read_data1 [31:0] $end
$var reg 32 \ read_data2 [31:0] $end
$var integer 32 ] i [31:0] $end
$upscope $end
$scope module write_back_mux $end
$var wire 32 ^ entrada1 [31:0] $end
$var wire 32 _ entrada2 [31:0] $end
$var wire 1 8 seletor $end
$var wire 32 ` saida [31:0] $end
$upscope $end
$upscope $end
$upscope $end
$enddefinitions $end
#0
$dumpvars
b10 `
b0 _
b10 ^
b100000 ]
b0 \
b0 [
b10 Z
b10 Y
b0 X
b10 W
b0 V
b100 U
b100 T
b10 S
b100 R
b10 Q
b10011 P
b1000000000000100010011 O
b0 N
b0 M
b10 L
b0 K
b10011 J
b0 I
b0 H
b0 G
b0 F
b10 E
b0 D
b0 C
b10 B
b0 A
b1000000000000100010011 @
bx ?
b0 >
1=
0<
0;
b0 :
09
08
17
b0 6
b10 5
b10 4
b10 3
b0 2
b0 1
b10 0
b1000000000000100010011 /
b10011 .
b0 -
b100 ,
b100 +
b10 *
b0 )
b0 (
b0 '
b10 &
b10 %
0$
1#
0"
0!
$end
#5000
b10 (
b10 M
b10 \
1"
#10000
0"
0#
#15000
b11 %
b11 Z
b11 `
b11 4
b11 E
b11 L
b11 ^
b11 5
b11 B
b0 (
b0 M
b0 \
b11 0
b11 Q
b11 &
b11 Y
b100 *
b100 W
b1100000000001000010011 /
b1100000000001000010011 @
b1100000000001000010011 O
b1000 +
b1000 T
b1000 U
b111 3
b111 S
b1000 ,
b1000 R
b100 -
b100 A
b100 V
1"
#20000
0"
#25000
b1 %
b1 Z
b1 `
b1 4
b1 E
b1 L
b1 ^
b100 5
b100 B
b11 (
b11 M
b11 \
b11 )
b11 C
b11 [
b110 6
b110 D
b110 I
19
07
1=
b100 0
b100 Q
b100011 P
b100 &
b100 Y
b100 '
b100 X
b10 2
b10 F
b100011 .
b100011 J
b10000100010001000100011 /
b10000100010001000100011 @
b10000100010001000100011 O
b1100 +
b1100 T
b1100 U
b1100 3
b1100 S
b1100 ,
b1100 R
b1000 -
b1000 A
b1000 V
1"
#30000
0"
#35000
1$
b0 4
b0 E
b0 L
b0 ^
b11 %
b11 Z
b11 `
b11 :
b11 N
b11 _
b0 5
b0 B
b0 (
b0 M
b0 \
18
1;
17
1=
09
b0 0
b0 Q
b11 P
b0 &
b0 Y
b111 *
b111 W
b11 .
b11 J
b100010001110000011 /
b100010001110000011 @
b100010001110000011 O
b10000 +
b10000 T
b10000 U
b1100 3
b1100 S
b10000 ,
b10000 R
b1100 -
b1100 A
b1100 V
1"
#40000
0"
#45000
1!
b0 %
b0 Z
b0 `
b0 :
b0 N
b0 _
b11 5
b11 B
b11 (
b11 M
b11 \
b1 6
b1 D
b1 I
b1 >
b1 H
b1 K
1<
08
07
0=
0;
b1100011 0
b1100011 Q
b1100011 P
b111 &
b111 Y
b111 '
b111 X
b0 2
b0 F
b0 *
b0 W
b1100011 .
b1100011 J
b11100111000000001100011 /
b11100111000000001100011 @
b11100111000000001100011 O
b1110011 +
b1110011 T
b1110011 U
b1110011 3
b1110011 S
b10100 ,
b10100 R
b10000 -
b10000 A
b10000 V
1"
#50000
0"
#55000
bx %
bx Z
bx `
bx 5
bx B
x$
bx 4
bx E
bx L
bx ^
0!
bx (
bx M
bx \
bx )
bx C
bx [
b0 6
b0 D
b0 I
b0 >
b0 H
b0 K
0<
b0 0
b0 Q
bx P
bx 1
bx G
bx &
bx Y
bx '
bx X
bx 2
bx F
bx *
bx W
bx .
bx J
bx /
bx @
bx O
b1110111 +
b1110111 T
b1110111 U
b1110011 3
b1110011 S
b1110111 ,
b1110111 R
b1110011 -
b1110011 A
b1110011 V
1"
